{"generatedAt":"2026-06-25T22:11:03.031Z","stocks":[{"symbol":"AMXB.MX","name":"AMERICA MOVIL SAB DE CV","etf":"XLC","sector":"Communication Services","industry":"Telecom Services","marketCap":1383262453760,"price":23.03,"returns":{"1d":0.56769025,"1w":0.5676855895196695,"3m":9.675521660682605,"6m":24.760337342904663,"ytd":24.62590706445944,"1y":41.992427167649055,"3y":18.618295823536045,"5y":56.0007351776774},"fiftyTwoWeekHigh":24.49,"fiftyTwoWeekLow":15.84,"pctFromHigh":-5.961616986525097,"pctFromLow":45.391414141414145,"trailingPE":15.882758,"forwardPE":11.675835,"priceToBook":3.7471528,"dividendYield":0.023580788,"fiftyDayAverage":22.8396,"twoHundredDayAverage":20.78175,"earningsDate":"2026-07-21T20:00:00.000Z","earningsEstimate":true,"epsForward":1.97245},{"symbol":"GFNORTEO.MX","name":"GRUPO FINANCIERO BANORTE","etf":"XLF","sector":"Financials","industry":"Banks - Regional","marketCap":516027285504,"price":185.85,"returns":{"1d":1.9529393,"1w":-2.38753795655569,"3m":-0.04442310471347355,"6m":9.290574310907559,"ytd":8.581309759032635,"1y":9.963565393456562,"3y":28.51530827029356,"5y":41.026244573483865},"fiftyTwoWeekHigh":210,"fiftyTwoWeekLow":155.5,"pctFromHigh":-11.5,"pctFromLow":19.517684887459797,"trailingPE":8.596208,"forwardPE":7.8811684,"priceToBook":2.2003198,"dividendYield":0,"fiftyDayAverage":188.5836,"twoHundredDayAverage":184.5908,"earningsDate":"2026-07-21T20:00:00.000Z","earningsEstimate":false,"epsForward":23.58153},{"symbol":"WALMEX.MX","name":"WAL-MART DE MEXICO SAB DE CV","etf":"XLP","sector":"Consumer Staples","industry":"Discount Stores","marketCap":883977879552,"price":51.12,"returns":{"1d":-0.75713336,"1w":-1.29399470090641,"3m":-8.800024511633424,"6m":-9.73457939327858,"ytd":-9.02737388732811,"1y":-16.05286530777086,"3y":-25.065669613696258,"5y":-19.530279830830395},"fiftyTwoWeekHigh":64.53,"fiftyTwoWeekLow":49.22,"pctFromHigh":-20.781032078103213,"pctFromLow":3.8602194229987674,"trailingPE":17.749998,"forwardPE":15.084229,"priceToBook":3.4999316,"dividendYield":0.0225199,"fiftyDayAverage":53.8806,"twoHundredDayAverage":57.11285,"earningsDate":"2026-07-22T20:00:00.000Z","earningsEstimate":false,"epsForward":3.38897},{"symbol":"FEMSAUBD.MX","name":"FOMENTO ECONOMICO MEXICANO SAB ","etf":"XLP","sector":"Consumer Staples","industry":"Beverages - Brewers","marketCap":902636371968,"price":218.97,"returns":{"1d":1.0055851,"1w":0.5036895135434349,"3m":19.27747953475864,"6m":18.82977376712556,"ytd":20.594444091859955,"1y":13.903836000820064,"3y":14.995139803813473,"5y":27.984992187629373},"fiftyTwoWeekHigh":224.57,"fiftyTwoWeekLow":156,"pctFromHigh":-2.493654539787149,"pctFromLow":40.36538461538461,"trailingPE":16.488705,"forwardPE":22.18024,"priceToBook":3.5056512,"dividendYield":0,"fiftyDayAverage":209.7876,"twoHundredDayAverage":189.364,"earningsDate":"2025-07-22T14:30:00.000Z","earningsEstimate":true,"epsForward":9.8723},{"symbol":"GMEXICOB.MX","name":"GRUPO MEXICO SAB DE CV","etf":"XLB","sector":"Materials","industry":"Other Industrial Metals & Mining","marketCap":1580432752640,"price":203.01,"returns":{"1d":2.9775767,"1w":-5.807463252912797,"3m":13.95976627403222,"6m":19.44500261465086,"ytd":19.381627935225666,"1y":93.42354260415917,"3y":132.94042420760488,"5y":125.3701891078741},"fiftyTwoWeekHigh":223.83,"fiftyTwoWeekLow":108.52,"pctFromHigh":-9.301702184693749,"pctFromLow":87.07150755621083,"trailingPE":16.279871,"forwardPE":14.426594,"priceToBook":3.8121645,"dividendYield":0.0017145176,"fiftyDayAverage":205.6274,"twoHundredDayAverage":181.85635,"earningsDate":"2026-07-27T20:00:00.000Z","earningsEstimate":true,"epsForward":14.071928},{"symbol":"CEMEXCPO.MX","name":"CEMEX S.A.B. DE C.V.","etf":"XLB","sector":"Materials","industry":"Building Materials","marketCap":322449276928,"price":21.72,"returns":{"1d":2.9871936,"1w":-0.7261653350067547,"3m":14.841058132538265,"6m":4.270835988501872,"ytd":5.127580774182306,"1y":68.09039976008927,"3y":75.41046526417733,"5y":39.9671626577439},"fiftyTwoWeekHigh":23.53,"fiftyTwoWeekLow":12.63,"pctFromHigh":-7.692307692307699,"pctFromLow":71.97149643705461,"trailingPE":35.606556,"forwardPE":21.72,"priceToBook":1.3784657,"dividendYield":0,"fiftyDayAverage":21.841,"twoHundredDayAverage":20.18115,"earningsDate":"2026-07-23T20:00:00.000Z","earningsEstimate":false,"epsForward":1},{"symbol":"TLEVISACPO.MX","name":"GRUPO TELEVISA SAB","etf":"XLC","sector":"Communication Services","industry":"Telecom Services","marketCap":25351585792,"price":9.62,"returns":{"1d":-1.2320317,"1w":-8.851279981140792,"3m":-6.628140468485668,"6m":-16.704823388792448,"ytd":-10.219364549956865,"1y":9.754762716781926,"3y":-47.58699078851937,"5y":-83.04885625722179},"fiftyTwoWeekHigh":12.18,"fiftyTwoWeekLow":7.57,"pctFromHigh":-21.01806239737275,"pctFromLow":27.080581241743708,"trailingPE":null,"forwardPE":8.548375,"priceToBook":0.2673039,"dividendYield":0,"fiftyDayAverage":9.968,"twoHundredDayAverage":10.25675,"earningsDate":"2026-07-28T20:00:00.000Z","earningsEstimate":true,"epsForward":1.12536},{"symbol":"BIMBOA.MX","name":"GRUPO BIMBO SAB DE CV","etf":"XLP","sector":"Consumer Staples","industry":"Packaged Foods","marketCap":241707155456,"price":56.16,"returns":{"1d":1.7207041,"1w":-2.971668914400908,"3m":-1.8010134336824564,"6m":-4.522272424185587,"ytd":-4.538505319111053,"1y":7.236968138502064,"3y":-39.049273452645046,"5y":27.1451242852975},"fiftyTwoWeekHigh":68.67,"fiftyTwoWeekLow":48.9,"pctFromHigh":-18.217562254259512,"pctFromLow":14.846625766871169,"trailingPE":20.647058,"forwardPE":16.303686,"priceToBook":1.9719794,"dividendYield":0,"fiftyDayAverage":57.6456,"twoHundredDayAverage":60.68775,"earningsDate":"2026-07-23T20:00:00.000Z","earningsEstimate":false,"epsForward":3.44462},{"symbol":"KIMBERA.MX","name":"KIMBERLY-CLARK DE MEXICO SAB DE","etf":"XLP","sector":"Consumer Staples","industry":"Household & Personal Products","marketCap":114662424576,"price":38.21,"returns":{"1d":2.5496533,"1w":0.6570902400574425,"3m":-4.955846712608235,"6m":1.7028068836383454,"ytd":0.024198236134694184,"1y":12.523531658827807,"3y":-4.2647100986167885,"5y":6.9146894821284235},"fiftyTwoWeekHigh":43.99,"fiftyTwoWeekLow":33.71,"pctFromHigh":-13.139349852239146,"pctFromLow":13.34915455354495,"trailingPE":14.752896,"forwardPE":13.764111,"priceToBook":45.326214,"dividendYield":0.059044555,"fiftyDayAverage":38.7698,"twoHundredDayAverage":38.83345,"earningsDate":"2026-07-21T20:00:00.000Z","earningsEstimate":false,"epsForward":2.77606},{"symbol":"ALSEA.MX","name":"ALSEA SAB DE CV","etf":"XLY","sector":"Consumer Discretionary","industry":"Restaurants","marketCap":35304972288,"price":44.32,"returns":{"1d":-1.2697699,"1w":-7.936573762177076,"3m":-22.276566679232303,"6m":-15.406401053740879,"ytd":-17.470424352805182,"1y":-13.253472115835379,"3y":-23.93111067535169,"5y":20.27722000021491},"fiftyTwoWeekHigh":63.39,"fiftyTwoWeekLow":44.14,"pctFromHigh":-30.083609402113897,"pctFromLow":0.4077933846850845,"trailingPE":17.380392,"forwardPE":9.790818,"priceToBook":3.955377,"dividendYield":0,"fiftyDayAverage":50.9208,"twoHundredDayAverage":53.9424,"earningsDate":"2026-07-21T20:00:00.000Z","earningsEstimate":true,"epsForward":4.52669},{"symbol":"GAPB.MX","name":"GPO AEROPORTUARIO DEL PACIFICO ","etf":"XLI","sector":"Industrials","industry":"Airports & Air Services","marketCap":262896877568,"price":441.83,"returns":{"1d":1.79242,"1w":2.302812753691626,"3m":5.917061136322019,"6m":-7.310599055279781,"ytd":-5.530366642135547,"1y":6.5444058109063405,"3y":33.447477911680124,"5y":95.81902629701483},"fiftyTwoWeekHigh":512.65,"fiftyTwoWeekLow":382.5,"pctFromHigh":-13.814493319028575,"pctFromLow":15.511111111111099,"trailingPE":22.280888,"forwardPE":16.620829,"priceToBook":8.687351,"dividendYield":0,"fiftyDayAverage":423.9472,"twoHundredDayAverage":439.47424,"earningsDate":"2026-07-20T20:00:00.000Z","earningsEstimate":true,"epsForward":26.58291},{"symbol":"ASURB.MX","name":"GPO AEROPORTUARIO DEL SURESTE S","etf":"XLI","sector":"Industrials","industry":"Airports & Air Services","marketCap":162945007616,"price":543.15,"returns":{"1d":2.0517528,"1w":3.649870806291915,"3m":-4.629139281580009,"6m":-4.201029849573416,"ytd":-6.190452174354959,"1y":-5.983829973195071,"3y":6.708356143261511,"5y":44.35023858809049},"fiftyTwoWeekHigh":652.9,"fiftyTwoWeekLow":479.01,"pctFromHigh":-16.809618624597945,"pctFromLow":13.39011711655289,"trailingPE":16.655933,"forwardPE":12.066399,"priceToBook":3.8436499,"dividendYield":0,"fiftyDayAverage":529.4136,"twoHundredDayAverage":574.40186,"earningsDate":"2026-07-21T20:00:00.000Z","earningsEstimate":true,"epsForward":45.01343},{"symbol":"OMAB.MX","name":"GRUPO AEROPORTUARIO DEL CENTRO ","etf":"XLI","sector":"Industrials","industry":"Airports & Air Services","marketCap":94229200896,"price":244.01,"returns":{"1d":3.192924,"1w":1.1769077671037564,"3m":1.1936652637934628,"6m":1.8429343344185583,"ytd":0.9762944033955279,"1y":1.5046125347774932,"3y":28.55294408988695,"5y":85.5076325528799},"fiftyTwoWeekHigh":289.74,"fiftyTwoWeekLow":207.8,"pctFromHigh":-15.783115897011124,"pctFromLow":17.425409047160723,"trailingPE":17.82396,"forwardPE":12.637701,"priceToBook":7.5423465,"dividendYield":0,"fiftyDayAverage":230.2334,"twoHundredDayAverage":243.0854,"earningsDate":"2026-07-27T20:00:00.000Z","earningsEstimate":true,"epsForward":19.3081},{"symbol":"PINFRA.MX","name":"PROMOTORA Y OPERADORA DE INFRST","etf":"XLI","sector":"Industrials","industry":"Infrastructure Operations","marketCap":104590786560,"price":279.04,"returns":{"1d":2.0069535,"1w":-2.1103951694208547,"3m":3.589267619841351,"6m":5.221452647522682,"ytd":5.707574876907586,"1y":28.98161125655102,"3y":50.0844090947476,"5y":70.62468845085533},"fiftyTwoWeekHigh":317.99,"fiftyTwoWeekLow":207.5,"pctFromHigh":-12.24881285575018,"pctFromLow":34.47710843373495,"trailingPE":7.88026,"forwardPE":13.264425,"priceToBook":1.6708382,"dividendYield":0.013789071,"fiftyDayAverage":281.6988,"twoHundredDayAverage":268.1586,"earningsDate":"2026-04-23T20:00:00.000Z","earningsEstimate":true,"epsForward":21.03672},{"symbol":"GCARSOA1.MX","name":"GRUPO CARSO S.A.B. DE C.V.","etf":"XLI","sector":"Industrials","industry":"Conglomerates","marketCap":304413966336,"price":135.12,"returns":{"1d":1.1150117,"1w":-5.040486054163964,"3m":10.428134788029212,"6m":17.601163498173108,"ytd":15.630419871346746,"1y":4.546488392700937,"3y":13.8395071959537,"5y":108.28790603304301},"fiftyTwoWeekHigh":156.1,"fiftyTwoWeekLow":113.1,"pctFromHigh":-13.440102498398455,"pctFromLow":19.469496021220166,"trailingPE":34.82474,"forwardPE":13.703854,"priceToBook":2.24743,"dividendYield":0,"fiftyDayAverage":138.3702,"twoHundredDayAverage":129.37805,"earningsDate":"2026-07-20T20:00:00.000Z","earningsEstimate":false,"epsForward":9.86},{"symbol":"LIVEPOLC-1.MX","name":"EL PUERTO DE LIVERPOOL SAB DE C","etf":"XLY","sector":"Consumer Discretionary","industry":"Department Stores","marketCap":136044994560,"price":101.36,"returns":{"1d":1.746635,"1w":1.6143958314472115,"3m":-3.5540729280202896,"6m":1.4318546855691068,"ytd":1.624550673483725,"1y":8.145043274237523,"3y":-9.254718482602044,"5y":14.802571671618978},"fiftyTwoWeekHigh":113.52,"fiftyTwoWeekLow":85.24,"pctFromHigh":-10.711768851303738,"pctFromLow":18.911309244486162,"trailingPE":8.1088,"forwardPE":6.0153375,"priceToBook":0.75585383,"dividendYield":0.029612528,"fiftyDayAverage":103.6296,"twoHundredDayAverage":100.2419,"earningsDate":"2026-07-27T20:00:00.000Z","earningsEstimate":false,"epsForward":16.85026},{"symbol":"ORBIA.MX","name":"ORBIA ADVANCE CORP S A B DE CV","etf":"XLI","sector":"Industrials","industry":"Conglomerates","marketCap":42323886080,"price":21.97,"returns":{"1d":1.712958,"1w":1.3369449635887776,"3m":13.09600289784531,"6m":38.0070094260511,"ytd":40.8433827965888,"1y":68.68703285853064,"3y":-42.9369916797645,"5y":-57.933409126627055},"fiftyTwoWeekHigh":24.04,"fiftyTwoWeekLow":12.01,"pctFromHigh":-8.610648918469222,"pctFromLow":82.9308909242298,"trailingPE":null,"forwardPE":16.943449,"priceToBook":1.1195513,"dividendYield":0,"fiftyDayAverage":22.085,"twoHundredDayAverage":19.06825,"earningsDate":"2026-07-22T20:00:00.000Z","earningsEstimate":false,"epsForward":1.2966663},{"symbol":"PE&OLES.MX","name":"INDUSTRIAS PENOLES SAB DE CV","etf":"XLB","sector":"Materials","industry":"Other Industrial Metals & Mining","marketCap":315059142656,"price":792.65,"returns":{"1d":5.267007,"1w":-4.361533461594277,"3m":1.3182640913742603,"6m":-1.6683951020577155,"ytd":-12.932129888075977,"1y":63.426617181657946,"3y":196.16252842801367,"5y":180.37601773015263},"fiftyTwoWeekHigh":1229.96,"fiftyTwoWeekLow":482,"pctFromHigh":-35.55481479072491,"pctFromLow":64.45020746887965,"trailingPE":9.709089,"forwardPE":7.8099756,"priceToBook":2.84113,"dividendYield":0.0005046548,"fiftyDayAverage":922.4858,"twoHundredDayAverage":887.8723,"earningsDate":"2026-07-27T20:00:00.000Z","earningsEstimate":true,"epsForward":101.492},{"symbol":"KOFUBL.MX","name":"COCA-COLA FEMSA S.A.B. DE C.V.","etf":"XLP","sector":"Consumer Staples","industry":"Beverages - Non-Alcoholic","marketCap":400601808896,"price":184.57,"returns":{"1d":0.42986646,"1w":-0.8236967031916862,"3m":11.72071452984089,"6m":11.290890745730579,"ytd":8.875800316370473,"1y":2.2548469636064397,"3y":23.364026462803082,"5y":75.3313855185215},"fiftyTwoWeekHigh":200.06,"fiftyTwoWeekLow":147.78,"pctFromHigh":-7.742677196840953,"pctFromLow":24.895114359182568,"trailingPE":20.018438,"forwardPE":13.955405,"priceToBook":2.8052156,"dividendYield":0.42115575,"fiftyDayAverage":182.6516,"twoHundredDayAverage":173.0441,"earningsDate":"2025-07-17T12:30:00.000Z","earningsEstimate":true,"epsForward":13.2257},{"symbol":"AC.MX","name":"ARCA CONTINENTAL SAB DE CV","etf":"XLP","sector":"Consumer Staples","industry":"Beverages - Non-Alcoholic","marketCap":358912884736,"price":211.35,"returns":{"1d":0.31802425,"1w":-1.211229389210061,"3m":11.30989650988694,"6m":11.538386380119874,"ytd":9.47552740215383,"1y":2.2690891097753365,"3y":18.39308336055086,"5y":85.05963012599432},"fiftyTwoWeekHigh":231,"fiftyTwoWeekLow":175.48,"pctFromHigh":-8.506493506493506,"pctFromLow":20.44107590608617,"trailingPE":19.05771,"forwardPE":14.64657,"priceToBook":2.8126748,"dividendYield":0.020315172,"fiftyDayAverage":215.041,"twoHundredDayAverage":199.0468,"earningsDate":"2026-07-23T20:00:00.000Z","earningsEstimate":false,"epsForward":14.43},{"symbol":"GRUMAB.MX","name":"GRUMA SAB DE CV","etf":"XLP","sector":"Consumer Staples","industry":"Packaged Foods","marketCap":96485859328,"price":282.75,"returns":{"1d":0.41194776,"1w":-3.422406193411362,"3m":-7.32930725047882,"6m":-8.850959249526227,"ytd":-9.091909855811252,"1y":-12.72958175867248,"3y":1.8039374456507176,"5y":25.009710273719463},"fiftyTwoWeekHigh":351.85,"fiftyTwoWeekLow":279.29,"pctFromHigh":-19.639050731845963,"pctFromLow":1.2388556697339626,"trailingPE":11.415018,"forwardPE":10.694429,"priceToBook":2.4157286,"dividendYield":0.001136404,"fiftyDayAverage":295.5354,"twoHundredDayAverage":313.0609,"earningsDate":"2026-07-22T20:00:00.000Z","earningsEstimate":true,"epsForward":26.439},{"symbol":"CUERVO.MX","name":"BECLE SAB DE CV","etf":"XLP","sector":"Consumer Staples","industry":"Beverages - Wineries & Distilleries","marketCap":52646641664,"price":14.66,"returns":{"1d":0.75601137,"1w":1.3853028995755778,"3m":-0.5471585401778327,"6m":-32.01664891238397,"ytd":-30.064038200180093,"1y":-36.617689905875075,"3y":-65.52708441501491,"5y":-72.53314087172956},"fiftyTwoWeekHigh":25.29,"fiftyTwoWeekLow":13.07,"pctFromHigh":-42.032423882957694,"pctFromLow":12.165263963274665,"trailingPE":6.663636,"forwardPE":10.526392,"priceToBook":0.7483028,"dividendYield":0,"fiftyDayAverage":14.3274,"twoHundredDayAverage":18.50865,"earningsDate":"2026-07-23T20:00:00.000Z","earningsEstimate":false,"epsForward":1.39269},{"symbol":"Q.MX","name":"QUALITAS CONTROLADORA SAB DE CV","etf":"XLF","sector":"Financials","industry":"Insurance - Property & Casualty","marketCap":69222645760,"price":175.52,"returns":{"1d":1.0768847,"1w":0.24577646570865852,"3m":5.810291198561444,"6m":-0.4025478164482763,"ytd":-6.202684758941601,"1y":-7.375519975786929,"3y":47.82791349045465,"5y":87.08486793527425},"fiftyTwoWeekHigh":196.97,"fiftyTwoWeekLow":155.74,"pctFromHigh":-10.889983246179613,"pctFromLow":12.700654937716704,"trailingPE":15.410008,"forwardPE":10.798387,"priceToBook":2.583076,"dividendYield":0,"fiftyDayAverage":171.9884,"twoHundredDayAverage":172.10416,"earningsDate":"2026-07-21T20:00:00.000Z","earningsEstimate":false,"epsForward":16.25428},{"symbol":"GENTERA.MX","name":"GENTERA SAB DE CV","etf":"XLF","sector":"Financials","industry":"Credit Services","marketCap":60200775680,"price":38.12,"returns":{"1d":0.68673617,"1w":-0.4739098803786703,"3m":-20.872509676294555,"6m":-12.487659733205334,"ytd":-16.120322348551667,"1y":0.28802984448418556,"3y":108.38786467474637,"5y":225.80709496933537},"fiftyTwoWeekHigh":54.97,"fiftyTwoWeekLow":35.55,"pctFromHigh":-30.65308350009096,"pctFromLow":7.229254571026722,"trailingPE":6.2800655,"forwardPE":5.620719,"priceToBook":1.5949124,"dividendYield":0,"fiftyDayAverage":43.3088,"twoHundredDayAverage":46.3344,"earningsDate":"2026-07-22T20:00:00.000Z","earningsEstimate":false,"epsForward":6.78205},{"symbol":"BBAJIOO.MX","name":"BANCO DEL BAJIO","etf":"XLF","sector":"Financials","industry":"Banks - Regional","marketCap":66517180416,"price":55.9,"returns":{"1d":1.8400477,"1w":1.5622953246449356,"3m":6.6219948068786465,"6m":17.82168869085919,"ytd":22.07007097347102,"1y":23.173680943849917,"3y":1.5438359078972894,"5y":59.734802627014545},"fiftyTwoWeekHigh":59.54,"fiftyTwoWeekLow":41.65,"pctFromHigh":-6.113537117903933,"pctFromLow":34.21368547418968,"trailingPE":7.3263435,"forwardPE":6.983912,"priceToBook":1.3346068,"dividendYield":0,"fiftyDayAverage":55.4742,"twoHundredDayAverage":51.0645,"earningsDate":"2026-07-22T20:00:00.000Z","earningsEstimate":true,"epsForward":8.00411},{"symbol":"RA.MX","name":"REGIONAL SAB DE CV","etf":"XLF","sector":"Financials","industry":"Banks - Regional","marketCap":42801598464,"price":130.52,"returns":{"1d":2.2563498,"1w":-1.2963600464010483,"3m":-10.453877560649374,"6m":-5.452458312814272,"ytd":-8.369360714959157,"1y":-16.89436357763246,"3y":-2.533105989334132,"5y":14.765618795153301},"fiftyTwoWeekHigh":165.75,"fiftyTwoWeekLow":125.5,"pctFromHigh":-21.254901960784313,"pctFromLow":4.0000000000000036,"trailingPE":6.5852675,"forwardPE":5.838881,"priceToBook":1.0917882,"dividendYield":0,"fiftyDayAverage":138.2486,"twoHundredDayAverage":145.28165,"earningsDate":"2026-07-27T20:00:00.000Z","earningsEstimate":true,"epsForward":22.3536},{"symbol":"CHDRAUIB.MX","name":"GRUPO COMERCIAL CHEDRAUI SAB DE","etf":"XLP","sector":"Consumer Staples","industry":"Grocery Stores","marketCap":87173718016,"price":90.83,"returns":{"1d":0.17646815,"1w":-1.3454805578600428,"3m":-9.289423204975435,"6m":-28.954249904873592,"ytd":-26.531321528413812,"1y":-37.77965861917895,"3y":-7.686699764028958,"5y":187.5993021699261},"fiftyTwoWeekHigh":164.99,"fiftyTwoWeekLow":88.75,"pctFromHigh":-44.94817867749561,"pctFromLow":2.3436619718309792,"trailingPE":13.337739,"forwardPE":10.135829,"priceToBook":1.6366947,"dividendYield":0.011139297,"fiftyDayAverage":96.7232,"twoHundredDayAverage":118.5022,"earningsDate":"2026-07-21T20:00:00.000Z","earningsEstimate":true,"epsForward":8.96128},{"symbol":"LABB.MX","name":"GENOMMA LAB INTERNACIONAL SAB","etf":"XLV","sector":"Health Care","industry":"Drug Manufacturers - Specialty & Generic","marketCap":14754287616,"price":15.09,"returns":{"1d":2.6530635,"1w":2.2346355018894997,"3m":-9.45284080040878,"6m":-18.38970616579138,"ytd":-16.021548243283547,"1y":-27.299816114900125,"3y":6.2028125465613755,"5y":-28.33838752917113},"fiftyTwoWeekHigh":23.6,"fiftyTwoWeekLow":14.24,"pctFromHigh":-36.05932203389831,"pctFromLow":5.969101123595499,"trailingPE":9.145454,"forwardPE":7.021381,"priceToBook":1.2562437,"dividendYield":0.04081633,"fiftyDayAverage":16.0552,"twoHundredDayAverage":17.58385,"earningsDate":"2026-07-22T20:00:00.000Z","earningsEstimate":false,"epsForward":2.14915},{"symbol":"MEGACPO.MX","name":"MEGACABLE HOLDINGS SAB DE CV","etf":"XLK","sector":"Technology","industry":"Other","marketCap":51689873408,"price":59.64,"returns":{"1d":2.2458384,"1w":3.062394447339315,"3m":2.6347466674479847,"6m":15.381801260965645,"ytd":12.559605119045358,"1y":17.29685222907912,"3y":39.4829316577856,"5y":-18.231489150484066},"fiftyTwoWeekHigh":69.32,"fiftyTwoWeekLow":49.79,"pctFromHigh":-13.96422388920946,"pctFromLow":19.7830889736895,"trailingPE":35.28994,"forwardPE":11.57072,"priceToBook":1.446695,"dividendYield":0,"fiftyDayAverage":59.6518,"twoHundredDayAverage":57.9435,"earningsDate":"2025-07-23T10:59:00.000Z","earningsEstimate":true,"epsForward":5.15439},{"symbol":"VESTA.MX","name":"CORPORACION INMOBILIARIA VESTA ","etf":"XLRE","sector":"Real Estate","industry":"Real Estate - Diversified","marketCap":54318448640,"price":58.54,"returns":{"1d":1.8795716,"1w":-2.0828886295724374,"3m":1.6137071880779814,"6m":5.657669530251567,"ytd":6.369620449578875,"1y":13.633378779472451,"3y":1.1036142699341696,"5y":46.678952471585205},"fiftyTwoWeekHigh":64.47,"fiftyTwoWeekLow":46.91,"pctFromHigh":-9.198076624786722,"pctFromLow":24.792155190790876,"trailingPE":8.737314,"forwardPE":18.01924,"priceToBook":0.9613599,"dividendYield":0.00147929,"fiftyDayAverage":60.3836,"twoHundredDayAverage":56.8772,"earningsDate":"2026-07-22T20:00:00.000Z","earningsEstimate":false,"epsForward":3.24875},{"symbol":"FUNO11.MX","name":"BANCO ACTINVER SA","etf":"XLRE","sector":"Real Estate","industry":"REIT - Diversified","marketCap":111461507072,"price":29.25,"returns":{"1d":0.8968618,"1w":-0.0003075208163352272,"3m":8.698551177264832,"6m":7.26305798432324,"ytd":8.295962414933967,"1y":14.263031174992662,"3y":13.773964918310128,"5y":26.52492029331607},"fiftyTwoWeekHigh":32.62,"fiftyTwoWeekLow":25.12,"pctFromHigh":-10.331085223789083,"pctFromLow":16.44108280254777,"trailingPE":5.6796117,"forwardPE":8.931543,"priceToBook":0.58448565,"dividendYield":0,"fiftyDayAverage":29.8492,"twoHundredDayAverage":28.43385,"earningsDate":"2026-07-28T20:00:00.000Z","earningsEstimate":true,"epsForward":3.27491},{"symbol":"GFINBURO.MX","name":"GRUPO FINANCIERO INBURSA SAB DE","etf":"XLF","sector":"Financials","industry":"Banks - Regional","marketCap":249988923392,"price":41.33,"returns":{"1d":1.125527,"1w":-1.796631982112558,"3m":-3.240455887147874,"6m":-6.004392196282026,"ytd":-4.444656005652931,"1y":-16.59331333829273,"3y":-5.144214037166947,"5y":103.14288822094616},"fiftyTwoWeekHigh":53.53,"fiftyTwoWeekLow":40.4,"pctFromHigh":-22.79095834111714,"pctFromLow":2.301980198019793,"trailingPE":8.103922,"forwardPE":6.724524,"priceToBook":1.0504245,"dividendYield":0,"fiftyDayAverage":42.9066,"twoHundredDayAverage":44.82395,"earningsDate":"2025-07-21T10:59:00.000Z","earningsEstimate":true,"epsForward":6.14616},{"symbol":"GCC.MX","name":"GCC SAB DE CV","etf":"XLB","sector":"Materials","industry":"Building Materials","marketCap":67979001856,"price":208.42,"returns":{"1d":4.059117,"1w":1.5621835951303922,"3m":16.72164685288429,"6m":8.290739011926249,"ytd":15.491707195567088,"1y":18.272894736263822,"3y":37.263914843443644,"5y":40.58130531315987},"fiftyTwoWeekHigh":221.21,"fiftyTwoWeekLow":151.41,"pctFromHigh":-5.78183626418336,"pctFromLow":37.65273099531075,"trailingPE":12.578154,"forwardPE":11.144305,"priceToBook":1.6737674,"dividendYield":0,"fiftyDayAverage":205.5034,"twoHundredDayAverage":189.13326,"earningsDate":"2026-07-28T20:00:00.000Z","earningsEstimate":false,"epsForward":18.70193},{"symbol":"BOLSAA.MX","name":"BOLSA MEXICANA DE VALORES SAB D","etf":"XLF","sector":"Financials","industry":"Financial Data & Stock Exchanges","marketCap":19398248448,"price":35,"returns":{"1d":-0.8217651,"1w":-3.0501711910908114,"3m":-5.334739221787743,"6m":-5.103418929310422,"ytd":-6.699376935034749,"1y":-16.20615364876805,"3y":-4.896836609678175,"5y":-20.003630934936552},"fiftyTwoWeekHigh":44.3,"fiftyTwoWeekLow":33.06,"pctFromHigh":-20.993227990970652,"pctFromLow":5.868118572292791,"trailingPE":12.195123,"forwardPE":10.640335,"priceToBook":2.403021,"dividendYield":0.05809011,"fiftyDayAverage":37.2908,"twoHundredDayAverage":36.79195,"earningsDate":"2026-07-21T20:00:00.000Z","earningsEstimate":false,"epsForward":3.28937},{"symbol":"ALPEKA.MX","name":"ALPEK SAB DE CV","etf":"XLB","sector":"Materials","industry":"Specialty Chemicals","marketCap":26118819840,"price":12.53,"returns":{"1d":-0.07974664,"1w":3.135513780309566,"3m":14.574008496520193,"6m":25.628385846848474,"ytd":30.480420163809498,"1y":25.125369755090432,"3y":-27.995255111392822,"5y":-45.343140824461415},"fiftyTwoWeekHigh":13,"fiftyTwoWeekLow":8.07,"pctFromHigh":-3.6153846153846203,"pctFromLow":55.266418835192056,"trailingPE":null,"forwardPE":21.910955,"priceToBook":1.1532444,"dividendYield":0,"fiftyDayAverage":11.9602,"twoHundredDayAverage":10.07225,"earningsDate":"2026-07-22T20:00:00.000Z","earningsEstimate":false,"epsForward":0.57186}],"sectors":[{"etf":"XLC","name":"Communication Services","returns":{"1d":-0.901069,"1w":-6.0007122507122475,"3m":-4.994150994330959,"6m":-9.38894610367319,"ytd":-10.312606184165817,"1y":1.6267205698334841,"3y":63.032736256948716,"5y":33.34175296792117},"marketCap":1408614039552,"count":2},{"etf":"XLF","name":"Financials","returns":{"1d":-0.502607,"1w":-1.6559337626494863,"3m":8.461850649350655,"6m":-2.5346462436177997,"ytd":-2.4100785101332844,"1y":5.175127902400645,"3y":59.172126265634326,"5y":43.68279569892473},"marketCap":1024156657664,"count":7},{"etf":"XLP","name":"Consumer Staples","returns":{"1d":-0.592136,"1w":-1.9277953031896278,"3m":3.4890888916286444,"6m":6.549885757806551,"ytd":8.05870236869206,"1y":3.120393120393117,"3y":12.414624347127345,"5y":20.275111047427984},"marketCap":3138804744192,"count":9},{"etf":"XLB","name":"Materials","returns":{"1d":1.32916,"1w":-1.669195751138075,"3m":6.996904024767803,"6m":14.260524575710832,"ytd":14.310915104740918,"1y":19.254658385093173,"3y":26.81017612524461,"5y":23.516797712651915},"marketCap":2312038993920,"count":5},{"etf":"XLY","name":"Consumer Discretionary","returns":{"1d":-1.49474,"1w":-4.313692385615397,"3m":3.34609773887673,"6m":-6.9757899056216655,"ytd":-5.074951846579012,"1y":5.736940298507465,"3y":36.25435749489121,"5y":31.48126667439972},"marketCap":171349966848,"count":2},{"etf":"XLI","name":"Industrials","returns":{"1d":2.16968,"1w":2.374200722824571,"3m":12.268292682926841,"6m":18.131656614910806,"ytd":18.69520371325426,"1y":27.985541498679268,"3y":74.6040777619725,"5y":79.62926829268294},"marketCap":971399725056,"count":6},{"etf":"XLV","name":"Health Care","returns":{"1d":1.48679,"1w":1.7588596835360182,"3m":7.486704882933903,"6m":0.4453336775525951,"ytd":0.5361757105942999,"1y":17.758777239709445,"3y":17.714242493003553,"5y":25.285783287715336},"marketCap":14754287616,"count":1},{"etf":"XLK","name":"Technology","returns":{"1d":0.830377,"1w":-1.0030036472859938,"3m":35.56371648916634,"6m":27.64177040110649,"ytd":28.20031951100923,"1y":51.98451910408433,"3y":113.12933025404158,"5y":160.39785553047406},"marketCap":51689873408,"count":1},{"etf":"XLRE","name":"Real Estate","returns":{"1d":0.179739,"1w":-1.130820399113075,"3m":10.67262347977167,"6m":10.56285643441608,"ytd":10.508054522924425,"1y":6.015216357584396,"3y":18.307243300610267,"5y":-0.6240249609984261},"marketCap":165779955712,"count":2}]}