{"generatedAt":"2026-06-26T21:56:35.686Z","stocks":[{"symbol":"AMXB.MX","name":"AMERICA MOVIL SAB DE CV","etf":"XLC","sector":"Communication Services","industry":"Telecom Services","marketCap":1393992531968,"price":23.21,"returns":{"1d":0.7815823,"1w":0.9567810424686911,"3m":5.2567098783949575,"6m":26.45701953007209,"ytd":25.162479619523367,"1y":43.04283175087957,"3y":19.1290028150963,"5y":54.193399675942544},"fiftyTwoWeekHigh":24.49,"fiftyTwoWeekLow":15.84,"pctFromHigh":-5.22662311147406,"pctFromLow":46.52777777777779,"trailingPE":16.006895,"forwardPE":11.767091,"priceToBook":3.77644,"dividendYield":0.023447677,"fiftyDayAverage":22.847,"twoHundredDayAverage":20.80565,"earningsDate":"2026-07-21T20:00:00.000Z","earningsEstimate":true,"epsForward":1.97245},{"symbol":"GFNORTEO.MX","name":"GRUPO FINANCIERO BANORTE","etf":"XLF","sector":"Financials","industry":"Banks - Regional","marketCap":505976029184,"price":182.23,"returns":{"1d":-1.9478129,"1w":-4.833952691804782,"3m":-3.7133492836710644,"6m":7.643252891442202,"ytd":6.611126628747527,"1y":9.242550819776639,"3y":27.124693756588186,"5y":40.79814034619193},"fiftyTwoWeekHigh":210,"fiftyTwoWeekLow":155.5,"pctFromHigh":-13.223809523809527,"pctFromLow":17.18971061093246,"trailingPE":8.43267,"forwardPE":7.727658,"priceToBook":2.1574616,"dividendYield":0,"fiftyDayAverage":188.3968,"twoHundredDayAverage":184.6439,"earningsDate":"2026-07-21T20:00:00.000Z","earningsEstimate":false,"epsForward":23.58153},{"symbol":"WALMEX.MX","name":"WAL-MART DE MEXICO SAB DE CV","etf":"XLP","sector":"Consumer Staples","industry":"Discount Stores","marketCap":878444347392,"price":50.8,"returns":{"1d":-0.6259775,"1w":0.953893574439121,"3m":-9.528054215354231,"6m":-10.46880959496012,"ytd":-9.544161188398164,"1y":-16.72131321545747,"3y":-26.440775073196562,"5y":-19.759914963448026},"fiftyTwoWeekHigh":64.53,"fiftyTwoWeekLow":49.22,"pctFromHigh":-21.276925461025886,"pctFromLow":3.210077204388462,"trailingPE":17.638887,"forwardPE":14.989805,"priceToBook":3.4780226,"dividendYield":0.022691706,"fiftyDayAverage":53.7554,"twoHundredDayAverage":57.08345,"earningsDate":"2026-07-22T20:00:00.000Z","earningsEstimate":false,"epsForward":3.38897},{"symbol":"FEMSAUBD.MX","name":"FOMENTO ECONOMICO MEXICANO SAB ","etf":"XLP","sector":"Consumer Staples","industry":"Beverages - Brewers","marketCap":925761863680,"price":224.58,"returns":{"1d":2.561995,"1w":2.5292702566294594,"3m":19.101794689372824,"6m":23.869541803185427,"ytd":24.190944232530683,"1y":16.777136803133217,"3y":17.718193846078677,"5y":31.14876536217676},"fiftyTwoWeekHigh":226.23,"fiftyTwoWeekLow":156,"pctFromHigh":-0.7293462405516427,"pctFromLow":43.961538461538474,"trailingPE":16.672606,"forwardPE":22.471775,"priceToBook":3.595466,"dividendYield":0,"fiftyDayAverage":210.2036,"twoHundredDayAverage":189.6783,"earningsDate":"2025-07-22T14:30:00.000Z","earningsEstimate":true,"epsForward":9.99387},{"symbol":"GMEXICOB.MX","name":"GRUPO MEXICO SAB DE CV","etf":"XLB","sector":"Materials","industry":"Other Industrial Metals & Mining","marketCap":1558012100608,"price":200.13,"returns":{"1d":-1.4186443,"1w":-6.582193700969427,"3m":9.697561206952756,"6m":21.234879501355138,"ytd":17.975648452794815,"1y":90.67202950352493,"3y":133.88300006444018,"5y":127.5273406352294},"fiftyTwoWeekHigh":223.83,"fiftyTwoWeekLow":110.71,"pctFromHigh":-10.588392976812766,"pctFromLow":80.76957817721977,"trailingPE":15.984824,"forwardPE":14.221932,"priceToBook":3.7580836,"dividendYield":0.0016649427,"fiftyDayAverage":205.561,"twoHundredDayAverage":182.2338,"earningsDate":"2026-07-27T20:00:00.000Z","earningsEstimate":true,"epsForward":14.071928},{"symbol":"CEMEXCPO.MX","name":"CEMEX S.A.B. DE C.V.","etf":"XLB","sector":"Materials","industry":"Building Materials","marketCap":319777046528,"price":21.54,"returns":{"1d":-0.82872194,"1w":-2.9330376314199356,"3m":11.22779037361343,"6m":2.285115728521916,"ytd":3.9165357147666953,"1y":65.51448940101628,"3y":73.38977786926549,"5y":34.96755419002588},"fiftyTwoWeekHigh":23.53,"fiftyTwoWeekLow":12.63,"pctFromHigh":-8.457288567785815,"pctFromLow":70.54631828978621,"trailingPE":35.311478,"forwardPE":21.54,"priceToBook":1.367042,"dividendYield":0,"fiftyDayAverage":21.8662,"twoHundredDayAverage":20.20155,"earningsDate":"2026-07-23T20:00:00.000Z","earningsEstimate":false,"epsForward":1},{"symbol":"TLEVISACPO.MX","name":"GRUPO TELEVISA SAB","etf":"XLC","sector":"Communication Services","industry":"Telecom Services","marketCap":25008996352,"price":9.49,"returns":{"1d":-1.3513526,"1w":-9.884654145089726,"3m":-8.757127206984265,"6m":-8.93242136974088,"ytd":-11.068152606462405,"1y":4.177301088428692,"3y":-46.83042716199078,"5y":-83.79464137358653},"fiftyTwoWeekHigh":12.18,"fiftyTwoWeekLow":7.57,"pctFromHigh":-22.085385878489326,"pctFromLow":25.36327608982827,"trailingPE":null,"forwardPE":8.432857,"priceToBook":0.2636917,"dividendYield":0,"fiftyDayAverage":9.9586,"twoHundredDayAverage":10.24985,"earningsDate":"2026-07-28T20:00:00.000Z","earningsEstimate":true,"epsForward":1.12536},{"symbol":"BIMBOA.MX","name":"GRUPO BIMBO SAB DE CV","etf":"XLP","sector":"Consumer Staples","industry":"Packaged Foods","marketCap":245365456896,"price":57.01,"returns":{"1d":1.51353,"1w":0.12829077876999406,"3m":-1.2367038777271233,"6m":-4.131775335100883,"ytd":-2.7140420278732194,"1y":9.600401222646028,"3y":-37.728942905095145,"5y":30.639874600081328},"fiftyTwoWeekHigh":68.67,"fiftyTwoWeekLow":48.9,"pctFromHigh":-16.979758264161937,"pctFromLow":16.584867075664622,"trailingPE":20.959558,"forwardPE":16.550447,"priceToBook":2.0018258,"dividendYield":0,"fiftyDayAverage":57.6272,"twoHundredDayAverage":60.65275,"earningsDate":"2026-07-23T20:00:00.000Z","earningsEstimate":false,"epsForward":3.44462},{"symbol":"KIMBERA.MX","name":"KIMBERLY-CLARK DE MEXICO SAB DE","etf":"XLP","sector":"Consumer Staples","industry":"Household & Personal Products","marketCap":116733018112,"price":38.9,"returns":{"1d":1.8058164,"1w":5.04733407763176,"3m":-4.135575309859846,"6m":2.1799081651380305,"ytd":1.992521140463083,"1y":14.098899972109209,"3y":-2.4297193910486357,"5y":7.870721216897408},"fiftyTwoWeekHigh":43.99,"fiftyTwoWeekLow":33.71,"pctFromHigh":-11.570811548079119,"pctFromLow":15.396024918421825,"trailingPE":15.019306,"forwardPE":14.012666,"priceToBook":46.144722,"dividendYield":0.057576552,"fiftyDayAverage":38.7174,"twoHundredDayAverage":38.84015,"earningsDate":"2026-07-21T20:00:00.000Z","earningsEstimate":false,"epsForward":2.77606},{"symbol":"ALSEA.MX","name":"ALSEA SAB DE CV","etf":"XLY","sector":"Consumer Discretionary","industry":"Restaurants","marketCap":35416494080,"price":44.46,"returns":{"1d":0.3158831,"1w":-4.632141525524901,"3m":-23.27461330619694,"6m":-16.378275347700068,"ytd":-17.172593475977493,"1y":-13.042561681594748,"3y":-24.995728219595648,"5y":21.171750683431227},"fiftyTwoWeekHigh":63.39,"fiftyTwoWeekLow":43.8,"pctFromHigh":-29.862754377662093,"pctFromLow":1.5068493150685036,"trailingPE":17.435293,"forwardPE":9.821746,"priceToBook":3.9678714,"dividendYield":0,"fiftyDayAverage":50.7234,"twoHundredDayAverage":53.88655,"earningsDate":"2026-07-21T20:00:00.000Z","earningsEstimate":true,"epsForward":4.52669},{"symbol":"GAPB.MX","name":"GPO AEROPORTUARIO DEL PACIFICO ","etf":"XLI","sector":"Industrials","industry":"Airports & Air Services","marketCap":261718753280,"price":439.85,"returns":{"1d":-0.44813174,"1w":0.15842047951680627,"3m":4.015106282361657,"6m":-8.730768541369116,"ytd":-5.211160069378153,"1y":6.6054579147608905,"3y":36.980179785743985,"5y":96.53307840758518},"fiftyTwoWeekHigh":512.65,"fiftyTwoWeekLow":382.5,"pctFromHigh":-14.200721739978539,"pctFromLow":14.993464052287585,"trailingPE":22.203434,"forwardPE":16.546345,"priceToBook":8.64842,"dividendYield":0,"fiftyDayAverage":424.737,"twoHundredDayAverage":439.3612,"earningsDate":"2026-07-20T20:00:00.000Z","earningsEstimate":true,"epsForward":26.58291},{"symbol":"ASURB.MX","name":"GPO AEROPORTUARIO DEL SURESTE S","etf":"XLI","sector":"Industrials","industry":"Airports & Air Services","marketCap":161382006784,"price":537.94,"returns":{"1d":-0.9592234,"1w":0.29378275163404055,"3m":-8.075782278842198,"6m":-8.44171656862747,"ytd":-7.259702490519814,"1y":-6.9068874826375435,"3y":6.245002577624362,"5y":41.059667118817},"fiftyTwoWeekHigh":652.9,"fiftyTwoWeekLow":479.01,"pctFromHigh":-17.607596875478627,"pctFromLow":12.302457151207701,"trailingPE":16.486055,"forwardPE":11.950655,"priceToBook":3.8067806,"dividendYield":0,"fiftyDayAverage":528.4912,"twoHundredDayAverage":573.924,"earningsDate":"2026-07-21T20:00:00.000Z","earningsEstimate":true,"epsForward":45.01343},{"symbol":"OMAB.MX","name":"GRUPO AEROPORTUARIO DEL CENTRO ","etf":"XLI","sector":"Industrials","industry":"Airports & Air Services","marketCap":94580621312,"price":244.92,"returns":{"1d":0.37293705,"1w":-0.9921853732770529,"3m":-2.211328396449744,"6m":0.9237532764515919,"ytd":1.0404854621163366,"1y":0.4471334132165339,"3y":27.661169762514746,"5y":84.81208747772055},"fiftyTwoWeekHigh":289.74,"fiftyTwoWeekLow":207.8,"pctFromHigh":-15.469041209360125,"pctFromLow":17.863330125120292,"trailingPE":17.877373,"forwardPE":12.684832,"priceToBook":7.5704746,"dividendYield":0,"fiftyDayAverage":230.2604,"twoHundredDayAverage":243.07014,"earningsDate":"2026-07-27T20:00:00.000Z","earningsEstimate":true,"epsForward":19.3081},{"symbol":"PINFRA.MX","name":"PROMOTORA Y OPERADORA DE INFRST","etf":"XLI","sector":"Industrials","industry":"Infrastructure Operations","marketCap":103934844928,"price":277.29,"returns":{"1d":-0.6271502,"1w":-1.5514688150900042,"3m":1.1494220850259609,"6m":4.185653700171528,"ytd":5.4126611143557,"1y":30.94515924718013,"3y":51.81240237715079,"5y":70.77498277627794},"fiftyTwoWeekHigh":317.99,"fiftyTwoWeekLow":207.5,"pctFromHigh":-12.799144627189529,"pctFromLow":33.63373493975905,"trailingPE":7.830839,"forwardPE":13.181237,"priceToBook":1.6603596,"dividendYield":0.013517775,"fiftyDayAverage":281.6018,"twoHundredDayAverage":268.3258,"earningsDate":"2026-04-23T20:00:00.000Z","earningsEstimate":true,"epsForward":21.03672},{"symbol":"GCARSOA1.MX","name":"GRUPO CARSO S.A.B. DE C.V.","etf":"XLI","sector":"Industrials","industry":"Conglomerates","marketCap":302228635648,"price":134.15,"returns":{"1d":-0.7178813,"1w":-12.10079505030913,"3m":7.886564608550941,"6m":16.748169817274686,"ytd":14.84163302757564,"1y":3.1634224930443224,"3y":12.958345640390021,"5y":106.73968048940773},"fiftyTwoWeekHigh":156.1,"fiftyTwoWeekLow":113.1,"pctFromHigh":-14.061499039077507,"pctFromLow":18.61184792219277,"trailingPE":34.57474,"forwardPE":13.605476,"priceToBook":2.2312963,"dividendYield":0,"fiftyDayAverage":138.091,"twoHundredDayAverage":129.3945,"earningsDate":"2026-07-27T20:00:00.000Z","earningsEstimate":false,"epsForward":9.86},{"symbol":"LIVEPOLC-1.MX","name":"EL PUERTO DE LIVERPOOL SAB DE C","etf":"XLY","sector":"Consumer Discretionary","industry":"Department Stores","marketCap":136474501120,"price":101.68,"returns":{"1d":0.31570607,"1w":1.566650483872749,"3m":-3.9433811422520506,"6m":-1.9828578191825414,"ytd":1.8002260780410495,"1y":8.482056399191393,"3y":-9.284143963231529,"5y":14.380862635543693},"fiftyTwoWeekHigh":113.52,"fiftyTwoWeekLow":85.24,"pctFromHigh":-10.42988019732205,"pctFromLow":19.286719849835766,"trailingPE":8.1344,"forwardPE":6.0343285,"priceToBook":0.7582401,"dividendYield":0.029104182,"fiftyDayAverage":103.5162,"twoHundredDayAverage":100.28535,"earningsDate":"2026-07-27T20:00:00.000Z","earningsEstimate":false,"epsForward":16.85026},{"symbol":"ORBIA.MX","name":"ORBIA ADVANCE CORP S A B DE CV","etf":"XLI","sector":"Industrials","industry":"Conglomerates","marketCap":42805497856,"price":22.22,"returns":{"1d":1.1379154,"1w":5.068392031698835,"3m":10.62589873593916,"6m":39.51812863747685,"ytd":42.385559113800895,"1y":88.99771512920236,"3y":-42.55135778224182,"5y":-57.292561771028836},"fiftyTwoWeekHigh":24.04,"fiftyTwoWeekLow":12.01,"pctFromHigh":-7.5707154742096545,"pctFromLow":85.01248959200665,"trailingPE":null,"forwardPE":16.886486,"priceToBook":1.1322908,"dividendYield":0,"fiftyDayAverage":22.0934,"twoHundredDayAverage":19.10295,"earningsDate":"2026-07-22T20:00:00.000Z","earningsEstimate":false,"epsForward":1.3158451},{"symbol":"PE&OLES.MX","name":"INDUSTRIAS PENOLES SAB DE CV","etf":"XLB","sector":"Materials","industry":"Other Industrial Metals & Mining","marketCap":308922122240,"price":777.21,"returns":{"1d":-1.9478966,"1w":-3.699806779022481,"3m":0.5043576545686221,"6m":-10.60899368464817,"ytd":-14.582363404305681,"1y":61.57832639106911,"3y":191.7295505238567,"5y":177.03677809739986},"fiftyTwoWeekHigh":1229.96,"fiftyTwoWeekLow":485.67,"pctFromHigh":-36.81014016715991,"pctFromLow":60.02841435542652,"trailingPE":9.483954,"forwardPE":7.6578455,"priceToBook":2.726098,"dividendYield":0.0004794045,"fiftyDayAverage":918.8732,"twoHundredDayAverage":888.22723,"earningsDate":"2026-07-27T20:00:00.000Z","earningsEstimate":true,"epsForward":101.492},{"symbol":"KOFUBL.MX","name":"COCA-COLA FEMSA S.A.B. DE C.V.","etf":"XLP","sector":"Consumer Staples","industry":"Beverages - Non-Alcoholic","marketCap":406201565184,"price":187.15,"returns":{"1d":1.3978363,"1w":-1.3455228268440749,"3m":11.972330691562888,"6m":8.573540720981967,"ytd":10.43802089811561,"1y":2.9656751249440134,"3y":23.91210791091804,"5y":77.64526056842746},"fiftyTwoWeekHigh":200.06,"fiftyTwoWeekLow":147.78,"pctFromHigh":-6.453064080775761,"pctFromLow":26.640952767627567,"trailingPE":20.210583,"forwardPE":14.150479,"priceToBook":2.8444278,"dividendYield":0.41935307,"fiftyDayAverage":182.7978,"twoHundredDayAverage":173.21115,"earningsDate":"2025-07-17T12:30:00.000Z","earningsEstimate":true,"epsForward":13.2257},{"symbol":"AC.MX","name":"ARCA CONTINENTAL SAB DE CV","etf":"XLP","sector":"Consumer Staples","industry":"Beverages - Non-Alcoholic","marketCap":359150649344,"price":211.49,"returns":{"1d":0.06624054,"1w":0.3846044744013284,"3m":8.571684863175491,"6m":8.41022301869117,"ytd":9.21110031905144,"1y":5.684115470947887,"3y":18.001642248783938,"5y":84.88712756447143},"fiftyTwoWeekHigh":231,"fiftyTwoWeekLow":175.48,"pctFromHigh":-8.445887445887445,"pctFromLow":20.52085707772966,"trailingPE":19.070333,"forwardPE":14.656272,"priceToBook":2.814538,"dividendYield":0.02025077,"fiftyDayAverage":215.1096,"twoHundredDayAverage":199.1572,"earningsDate":"2026-07-23T20:00:00.000Z","earningsEstimate":false,"epsForward":14.43},{"symbol":"GRUMAB.MX","name":"GRUMA SAB DE CV","etf":"XLP","sector":"Consumer Staples","industry":"Packaged Foods","marketCap":96632594432,"price":283.18,"returns":{"1d":0.15207522,"1w":-1.7743304869500491,"3m":-7.722751289611921,"6m":-8.644802692216672,"ytd":-8.6330289964325,"1y":-12.253759998061597,"3y":3.1820164422373978,"5y":25.4571956141301},"fiftyTwoWeekHigh":351.85,"fiftyTwoWeekLow":279.29,"pctFromHigh":-19.516839562313493,"pctFromLow":1.3928175015217148,"trailingPE":11.395573,"forwardPE":10.710692,"priceToBook":2.379014,"dividendYield":0.0011317418,"fiftyDayAverage":295.136,"twoHundredDayAverage":312.8202,"earningsDate":"2026-07-22T20:00:00.000Z","earningsEstimate":true,"epsForward":26.439},{"symbol":"CUERVO.MX","name":"BECLE SAB DE CV","etf":"XLP","sector":"Consumer Staples","industry":"Beverages - Wineries & Distilleries","marketCap":52718469120,"price":14.68,"returns":{"1d":0.13642877,"1w":1.7280864382918821,"3m":-2.062178038680429,"6m":-31.182539507748572,"ytd":-29.5354006254384,"1y":-33.84245222802636,"3y":-65.15963460529198,"5y":-71.5169228089383},"fiftyTwoWeekHigh":25.29,"fiftyTwoWeekLow":13.07,"pctFromHigh":-41.953341241597464,"pctFromLow":12.318286151491954,"trailingPE":6.672727,"forwardPE":10.540752,"priceToBook":0.7493237,"dividendYield":0,"fiftyDayAverage":14.2926,"twoHundredDayAverage":18.47585,"earningsDate":"2026-07-23T20:00:00.000Z","earningsEstimate":false,"epsForward":1.39269},{"symbol":"Q.MX","name":"QUALITAS CONTROLADORA SAB DE CV","etf":"XLF","sector":"Financials","industry":"Insurance - Property & Casualty","marketCap":69100388352,"price":175.21,"returns":{"1d":-0.17661665,"1w":0.42263215654114106,"3m":3.756415942265164,"6m":-2.373704218439542,"ytd":-6.155243200864703,"1y":-8.037052574558771,"3y":48.42761113585783,"5y":85.32309753622869},"fiftyTwoWeekHigh":196.97,"fiftyTwoWeekLow":155.74,"pctFromHigh":-11.047367619434423,"pctFromLow":12.501605239501723,"trailingPE":15.369299,"forwardPE":10.779315,"priceToBook":2.5785139,"dividendYield":0,"fiftyDayAverage":172.1926,"twoHundredDayAverage":172.1159,"earningsDate":"2026-07-21T20:00:00.000Z","earningsEstimate":false,"epsForward":16.25428},{"symbol":"GENTERA.MX","name":"GENTERA SAB DE CV","etf":"XLF","sector":"Financials","industry":"Credit Services","marketCap":60595585024,"price":38.37,"returns":{"1d":0.6558237,"1w":1.4010248779018468,"3m":-22.619317520764426,"6m":-16.138491836303032,"ytd":-15.323765678655263,"1y":0.6030125234187125,"3y":111.06145920937809,"5y":230.60229343296072},"fiftyTwoWeekHigh":54.97,"fiftyTwoWeekLow":35.55,"pctFromHigh":-30.198289976350743,"pctFromLow":7.9324894514767985,"trailingPE":6.321252,"forwardPE":5.6575813,"priceToBook":1.6053722,"dividendYield":0,"fiftyDayAverage":43.0934,"twoHundredDayAverage":46.2964,"earningsDate":"2026-07-22T20:00:00.000Z","earningsEstimate":false,"epsForward":6.78205},{"symbol":"BBAJIOO.MX","name":"BANCO DEL BAJIO","etf":"XLF","sector":"Financials","industry":"Banks - Regional","marketCap":66683768832,"price":56.04,"returns":{"1d":0.2504461,"1w":0.17899805893904386,"3m":4.908476358596431,"6m":21.47894149426685,"ytd":22.859385277105417,"1y":25.017680930742088,"3y":0.8619500317816886,"5y":60.905709359911555},"fiftyTwoWeekHigh":59.54,"fiftyTwoWeekLow":41.65,"pctFromHigh":-5.878401074907624,"pctFromLow":34.54981992797119,"trailingPE":7.344692,"forwardPE":7.001403,"priceToBook":1.3379493,"dividendYield":0,"fiftyDayAverage":55.4474,"twoHundredDayAverage":51.10325,"earningsDate":"2026-07-22T20:00:00.000Z","earningsEstimate":true,"epsForward":8.00411},{"symbol":"RA.MX","name":"REGIONAL SAB DE CV","etf":"XLF","sector":"Financials","industry":"Banks - Regional","marketCap":43008192512,"price":131.15,"returns":{"1d":0.48267668,"1w":-0.12810825718921137,"3m":-12.91811633347001,"6m":-8.72125185258129,"ytd":-7.838029846880431,"1y":-17.46223087454763,"3y":-3.0954011178548484,"5y":18.394344538553796},"fiftyTwoWeekHigh":165.75,"fiftyTwoWeekLow":125.5,"pctFromHigh":-20.87481146304675,"pctFromLow":4.501992031872515,"trailingPE":6.613716,"forwardPE":5.867064,"priceToBook":1.097058,"dividendYield":0,"fiftyDayAverage":137.9448,"twoHundredDayAverage":145.2026,"earningsDate":"2026-07-27T20:00:00.000Z","earningsEstimate":true,"epsForward":22.3536},{"symbol":"CHDRAUIB.MX","name":"GRUPO COMERCIAL CHEDRAUI SAB DE","etf":"XLP","sector":"Consumer Staples","industry":"Grocery Stores","marketCap":87000965120,"price":90.65,"returns":{"1d":-0.19817273,"1w":0.5762620970261167,"3m":-9.999159493889266,"6m":-27.462548937700916,"ytd":-26.67702708641363,"1y":-38.270616577569825,"3y":-7.672892829669507,"5y":186.84744712059342},"fiftyTwoWeekHigh":164.99,"fiftyTwoWeekLow":88.75,"pctFromHigh":-45.05727619855748,"pctFromLow":2.140845070422537,"trailingPE":13.311307,"forwardPE":10.115743,"priceToBook":1.6334511,"dividendYield":0.011119674,"fiftyDayAverage":96.4612,"twoHundredDayAverage":118.20675,"earningsDate":"2026-07-21T20:00:00.000Z","earningsEstimate":true,"epsForward":8.96128},{"symbol":"LABB.MX","name":"GENOMMA LAB INTERNACIONAL SAB","etf":"XLV","sector":"Health Care","industry":"Drug Manufacturers - Specialty & Generic","marketCap":14627179520,"price":14.96,"returns":{"1d":-0.8614984,"1w":1.7776866844574641,"3m":-11.08866843161492,"6m":-17.84886487931867,"ytd":-16.794471832917537,"1y":-27.689475731484563,"3y":5.973212753564567,"5y":-29.800231300864056},"fiftyTwoWeekHigh":23.6,"fiftyTwoWeekLow":14.24,"pctFromHigh":-36.610169491525426,"pctFromLow":5.0561797752809,"trailingPE":9.066667,"forwardPE":6.9608917,"priceToBook":1.2454213,"dividendYield":0.03976143,"fiftyDayAverage":15.9984,"twoHundredDayAverage":17.54575,"earningsDate":"2026-07-22T20:00:00.000Z","earningsEstimate":false,"epsForward":2.14915},{"symbol":"MEGACPO.MX","name":"MEGACABLE HOLDINGS SAB DE CV","etf":"XLK","sector":"Technology","industry":"Other","marketCap":52201226240,"price":60.23,"returns":{"1d":0.9892692,"1w":4.4492512618595725,"3m":-1.9776089001822186,"6m":16.572824033270976,"ytd":13.876218362143973,"1y":18.88028292038497,"3y":42.7241370299721,"5y":-17.1723655962211},"fiftyTwoWeekHigh":69.32,"fiftyTwoWeekLow":49.79,"pctFromHigh":-13.113098672821689,"pctFromLow":20.96806587668205,"trailingPE":35.639053,"forwardPE":11.685185,"priceToBook":1.4610068,"dividendYield":0,"fiftyDayAverage":59.6772,"twoHundredDayAverage":57.95785,"earningsDate":"2025-07-23T10:59:00.000Z","earningsEstimate":true,"epsForward":5.15439},{"symbol":"VESTA.MX","name":"CORPORACION INMOBILIARIA VESTA ","etf":"XLRE","sector":"Real Estate","industry":"Real Estate - Diversified","marketCap":54791667712,"price":59.05,"returns":{"1d":0.87119627,"1w":0.8196311359804014,"3m":1.6686050085516797,"6m":6.692441919335735,"ytd":7.741686437208443,"1y":14.431255290578733,"3y":2.1954750078114955,"5y":47.46002351274518},"fiftyTwoWeekHigh":64.47,"fiftyTwoWeekLow":46.91,"pctFromHigh":-8.40701101287421,"pctFromLow":25.879343423577073,"trailingPE":8.787203,"forwardPE":18.176222,"priceToBook":0.96973526,"dividendYield":0.0014519986,"fiftyDayAverage":60.3188,"twoHundredDayAverage":56.90695,"earningsDate":"2026-07-22T20:00:00.000Z","earningsEstimate":false,"epsForward":3.24875},{"symbol":"FUNO11.MX","name":"BANCO ACTINVER SA","etf":"XLRE","sector":"Real Estate","industry":"REIT - Diversified","marketCap":113023877120,"price":29.66,"returns":{"1d":1.4017088,"1w":1.2628539436189925,"3m":7.559558944879967,"6m":10.36895355182942,"ytd":9.551402629044418,"1y":15.317267640321475,"3y":15.995602783694096,"5y":28.158053759180348},"fiftyTwoWeekHigh":32.62,"fiftyTwoWeekLow":25.12,"pctFromHigh":-9.074187614960138,"pctFromLow":18.073248407643305,"trailingPE":5.759223,"forwardPE":9.056738,"priceToBook":0.5926784,"dividendYield":0,"fiftyDayAverage":29.8208,"twoHundredDayAverage":28.43715,"earningsDate":"2026-07-28T20:00:00.000Z","earningsEstimate":true,"epsForward":3.27491},{"symbol":"GFINBURO.MX","name":"GRUPO FINANCIERO INBURSA SAB DE","etf":"XLF","sector":"Financials","industry":"Banks - Regional","marketCap":248234819584,"price":41.04,"returns":{"1d":-0.70167166,"1w":-2.721457268838833,"3m":-4.572231704489738,"6m":-4.682815237942265,"ytd":-5.210031671341824,"1y":-13.630055435146417,"3y":-6.225795469903289,"5y":102.0106357872184},"fiftyTwoWeekHigh":53.53,"fiftyTwoWeekLow":40.4,"pctFromHigh":-23.33271062955352,"pctFromLow":1.5841584158415856,"trailingPE":8.047059,"forwardPE":6.67734,"priceToBook":1.043054,"dividendYield":0,"fiftyDayAverage":42.8506,"twoHundredDayAverage":44.77305,"earningsDate":"2025-07-21T10:59:00.000Z","earningsEstimate":true,"epsForward":6.14616},{"symbol":"GCC.MX","name":"GCC SAB DE CV","etf":"XLB","sector":"Materials","industry":"Building Materials","marketCap":67962691584,"price":208.37,"returns":{"1d":-0.023991484,"1w":1.6335796467228647,"3m":13.277886299722866,"6m":12.659453635351483,"ytd":15.589813125959282,"1y":17.366813310254344,"3y":36.615097378559085,"5y":39.122884067789215},"fiftyTwoWeekHigh":221.21,"fiftyTwoWeekLow":151.41,"pctFromHigh":-5.8044392206500595,"pctFromLow":37.61970807740573,"trailingPE":12.522236,"forwardPE":11.098197,"priceToBook":1.673366,"dividendYield":0,"fiftyDayAverage":205.7922,"twoHundredDayAverage":189.2962,"earningsDate":"2026-07-28T20:00:00.000Z","earningsEstimate":false,"epsForward":18.775122},{"symbol":"BOLSAA.MX","name":"BOLSA MEXICANA DE VALORES SAB D","etf":"XLF","sector":"Financials","industry":"Financial Data & Stock Exchanges","marketCap":19376076800,"price":34.96,"returns":{"1d":-0.11428833,"1w":-1.1562363023350457,"3m":-4.521015728116211,"6m":-11.732419152402926,"ytd":-6.40714082482944,"1y":-16.504208648007776,"3y":-4.986767641290513,"5y":-19.32838258462634},"fiftyTwoWeekHigh":44.3,"fiftyTwoWeekLow":33.06,"pctFromHigh":-21.08352144469525,"pctFromLow":5.747126436781613,"trailingPE":12.181185,"forwardPE":10.628175,"priceToBook":2.4002748,"dividendYield":0.058571428,"fiftyDayAverage":37.2582,"twoHundredDayAverage":36.77805,"earningsDate":"2026-07-21T20:00:00.000Z","earningsEstimate":false,"epsForward":3.28937},{"symbol":"ALPEKA.MX","name":"ALPEK SAB DE CV","etf":"XLB","sector":"Materials","industry":"Specialty Chemicals","marketCap":26139664384,"price":12.54,"returns":{"1d":0.079810284,"1w":2.880397037112658,"3m":14.468569232775025,"6m":33.83263001433866,"ytd":30.47983243319237,"1y":26.64607895123153,"3y":-27.536418275063085,"5y":-44.95830756726832},"fiftyTwoWeekHigh":13,"fiftyTwoWeekLow":8.07,"pctFromHigh":-3.538461538461546,"pctFromLow":55.390334572490694,"trailingPE":null,"forwardPE":21.928444,"priceToBook":1.1541648,"dividendYield":0,"fiftyDayAverage":11.9982,"twoHundredDayAverage":10.09195,"earningsDate":"2026-07-22T20:00:00.000Z","earningsEstimate":false,"epsForward":0.57186}],"sectors":[{"etf":"XLC","name":"Communication Services","returns":{"1d":0.568288,"1w":-2.765567765567767,"3m":-4.720028715003577,"6m":-8.983370478313034,"ytd":-9.80292218824328,"1y":0.9027843770787802,"3y":65.02953061858877,"5y":33.54295057225507},"marketCap":1419001528320,"count":2},{"etf":"XLF","name":"Financials","returns":{"1d":0.224507,"1w":-0.8880666049953634,"3m":8.573165788406968,"6m":-3.163412870571225,"ytd":-2.1909804637575414,"1y":3.8580845288871624,"3y":61.452682338758294,"5y":48.393351800554015},"marketCap":1012974860288,"count":7},{"etf":"XLP","name":"Consumer Staples","returns":{"1d":0.917318,"1w":1.2308795411089646,"3m":3.9258986627407566,"6m":8.769902413970199,"ytd":9.049948506694117,"1y":4.155908029017574,"3y":15.126393041587383,"5y":20.945174186179315},"marketCap":3168008929280,"count":9},{"etf":"XLB","name":"Materials","returns":{"1d":-0.462966,"1w":-0.8073817762399127,"3m":4.432301153612639,"6m":12.98445368951171,"ytd":13.781697905181911,"1y":17.72758384668036,"3y":28.582108148517314,"5y":25.761637825980998},"marketCap":2280813625344,"count":5},{"etf":"XLY","name":"Consumer Discretionary","returns":{"1d":0.899871,"1w":-0.9697809334141438,"3m":3.287275354465824,"6m":-6.514631355239498,"ytd":-4.220752030818186,"1y":6.104462380554776,"3y":36.74079387852702,"5y":32.15853940374394},"marketCap":171890995200,"count":2},{"etf":"XLI","name":"Industrials","returns":{"1d":-1.58592,"1w":0.8908685968819663,"3m":9.751665657177465,"6m":15.377268385864351,"ytd":16.81279009798864,"1y":24.913828760512892,"3y":73.81294964028775,"5y":79.54815695600475},"marketCap":966650359808,"count":6},{"etf":"XLV","name":"Health Care","returns":{"1d":3.0264,"1w":6.389755158914467,"3m":9.641684901531722,"6m":3.2453316162266432,"ytd":3.5788113695090384,"1y":19.85349080580057,"3y":21.913017031630154,"5y":28.097787009666852},"marketCap":14627179520,"count":1},{"etf":"XLK","name":"Technology","returns":{"1d":-1.87463,"1w":-2.524219590958021,"3m":32.4290728283124,"6m":24.765775695783976,"ytd":25.797041050218805,"1y":46.505419834978156,"3y":111.01013631597345,"5y":152.59414225941424},"marketCap":52201226240,"count":1},{"etf":"XLRE","name":"Real Estate","returns":{"1d":1.45773,"1w":2.8883329542870317,"3m":12.341693568413215,"6m":12.565314754914159,"ytd":12.118959107806692,"1y":7.051585423568385,"3y":22.50203086921203,"5y":0.4440497335701732},"marketCap":167815544832,"count":2}]}