{"TECH":{"why":"Agreed to be acquired by Merck KGaA","ts":"2026-06-26T23:54:27.218Z","tf":"1w"},"ORCL":{"why":"AI financing concerns escalated","ts":"2026-06-28T13:28:02.358Z","tf":"1w"},"MU":{"why":"AI-fueled forecast shatters projections","ts":"2026-06-26T23:54:28.837Z","tf":"ytd"},"INTC":{"why":"Q1 earnings beat, AI optimism, Apple chip deal","ts":"2026-06-26T23:54:29.198Z","tf":"ytd"},"DELL":{"why":"First Quarter Fiscal 2027 Financial Results","ts":"2026-06-26T23:54:34.371Z","tf":"ytd"},"TTD":{"why":"earnings suggest problems intensifying","ts":"2026-06-23T02:23:40.429Z","tf":"ytd"},"CTSH":{"why":"","ts":"2026-06-26T23:54:29.934Z","tf":"ytd"},"ACN":{"why":"AI threat mounts, disappointing outlook in uncertain consultancy market","ts":"2026-06-26T23:54:30.015Z","tf":"ytd"},"BSX":{"why":"","ts":"2026-06-23T02:23:40.499Z","tf":"ytd"},"CSGP":{"why":"","ts":"2026-06-23T02:23:41.136Z","tf":"ytd"},"INTU":{"why":"","ts":"2026-06-23T02:23:41.381Z","tf":"ytd"},"LITE":{"why":"New U.S. manufacturing facility for AI data center lasers","ts":"2026-06-24T23:56:43.253Z","tf":"1y"},"CIEN":{"why":"","ts":"2026-06-23T23:11:27.015Z","tf":"1y"},"IT":{"why":"","ts":"2026-06-23T23:11:23.069Z","tf":"1y"},"FISV":{"why":"CEO's sudden departure after 71% stock drop","ts":"2026-06-23T02:23:41.806Z","tf":"1y"},"MRVL":{"why":"added to S&P 500 index","ts":"2026-06-24T23:56:48.998Z","tf":"ytd"},"ADBE":{"why":"CFO departure, stock sinks to 7-year low","ts":"2026-06-23T02:23:45.289Z","tf":"ytd"},"FOUR":{"why":"","ts":"2026-06-26T23:54:32.971Z","tf":"1w"},"JEF":{"why":"","ts":"2026-06-26T23:54:33.869Z","tf":"1w"},"KD":{"why":"","ts":"2026-06-23T02:23:48.634Z","tf":"ytd"},"EPAM":{"why":"","ts":"2026-06-24T23:56:49.528Z","tf":"ytd"},"GTM":{"why":"","ts":"2026-06-26T23:54:34.180Z","tf":"ytd"},"FMC":{"why":"","ts":"2026-06-26T23:54:34.747Z","tf":"1y"},"MXL":{"why":"","ts":"2026-06-23T02:23:51.935Z","tf":"ytd"},"ICHR":{"why":"","ts":"2026-06-23T02:23:51.981Z","tf":"ytd"},"UCTT":{"why":"","ts":"2026-06-23T02:23:52.676Z","tf":"ytd"},"VSH":{"why":"","ts":"2026-06-23T02:23:52.753Z","tf":"ytd"},"VITL":{"why":"","ts":"2026-06-23T02:23:52.815Z","tf":"ytd"},"VRRM":{"why":"Avis Budget Group terminated agreement","ts":"2026-06-23T02:23:54.071Z","tf":"ytd"},"VICR":{"why":"","ts":"2026-06-23T23:11:28.463Z","tf":"1y"},"CCOI":{"why":"","ts":"2026-06-26T23:54:36.572Z","tf":"1y"},"GOGO":{"why":"","ts":"2026-06-23T02:23:53.983Z","tf":"1y"},"DFTX":{"why":"","ts":"2026-06-28T13:28:07.847Z","tf":"1w"},"APGE":{"why":"Agreed to be acquired by AbbVie for $10.9 billion","ts":"2026-06-28T13:28:07.867Z","tf":"1w"},"LPRO":{"why":"Agreed to be acquired by ANV","ts":"2026-06-28T13:28:08.518Z","tf":"1w"},"AGL":{"why":"Q1 earnings beat, stock up 115% after earnings","ts":"2026-06-23T02:23:57.342Z","tf":"ytd"},"AEHR":{"why":"","ts":"2026-06-23T02:23:57.466Z","tf":"ytd"},"UPB":{"why":"","ts":"2026-06-23T02:23:58.030Z","tf":"ytd"},"ERAS":{"why":"","ts":"2026-06-23T02:23:58.639Z","tf":"1y"},"KOD":{"why":"Positive topline results in GLOW2 Phase 3 study","ts":"2026-06-23T02:23:59.098Z","tf":"1y"},"ASST":{"why":"","ts":"2026-06-28T13:28:08.356Z","tf":"1y"},"ERF.PA":{"why":"","ts":"2026-06-28T13:28:10.255Z","tf":"1w"},"CA.PA":{"why":"GXO renews long-term partnership in Belgium","ts":"2026-06-26T23:54:40.604Z","tf":"1w"},"AI.PA":{"why":"","ts":"2026-06-28T13:28:10.487Z","tf":"1w"},"URW.PA":{"why":"Legal structure simplification completed through de-stapling","ts":"2026-06-26T23:54:40.933Z","tf":"1w"},"TEP.PA":{"why":"","ts":"2026-06-26T23:54:40.357Z","tf":"1w"},"HO.PA":{"why":"","ts":"2026-06-28T13:28:11.405Z","tf":"1w"},"RNO.PA":{"why":"","ts":"2026-06-28T13:28:11.520Z","tf":"1w"},"BNP.PA":{"why":"","ts":"2026-06-23T02:24:04.604Z","tf":"ytd"},"TTE.PA":{"why":"Flags earnings boost from strong trading and oil price spike","ts":"2026-06-26T23:54:41.980Z","tf":"ytd"},"VIE.PA":{"why":"Works with Amazon to develop reclaimed water for data centers","ts":"2026-06-26T23:54:42.084Z","tf":"ytd"},"CAP.PA":{"why":"new targets building on AI consulting, but shares fall","ts":"2026-06-26T23:54:42.542Z","tf":"ytd"},"GLE.PA":{"why":"","ts":"2026-06-28T13:28:11.698Z","tf":"1y"},"KER.PA":{"why":"","ts":"2026-06-23T02:24:05.137Z","tf":"1y"},"ENGI.PA":{"why":"","ts":"2026-06-28T13:28:11.693Z","tf":"1y"},"UNA.AS":{"why":"","ts":"2026-06-26T23:54:44.815Z","tf":"1w"},"ADYEN.AS":{"why":"","ts":"2026-06-28T13:28:14.060Z","tf":"1w"},"REN.AS":{"why":"","ts":"2026-06-26T00:06:16.603Z","tf":"ytd"},"INGA.AS":{"why":"","ts":"2026-06-26T00:06:17.670Z","tf":"1y"},"034730.KS":{"why":"SK Hynix Nasdaq debut, blockbuster listing","ts":"2026-06-26T23:54:47.368Z","tf":"1w"},"005380.KS":{"why":"","ts":"2026-06-28T13:28:16.300Z","tf":"1w"},"010130.KS":{"why":"","ts":"2026-06-24T12:10:59.476Z","tf":"ytd"},"035420.KS":{"why":"","ts":"2026-06-26T23:54:48.592Z","tf":"ytd"},"035720.KS":{"why":"","ts":"2026-06-23T02:24:13.357Z","tf":"ytd"},"011200.KS":{"why":"","ts":"2026-06-23T02:24:14.054Z","tf":"1y"},"4661.T":{"why":"","ts":"2026-06-28T13:28:19.039Z","tf":"1w"},"6758.T":{"why":"","ts":"2026-06-26T23:54:50.886Z","tf":"1w"},"8411.T":{"why":"","ts":"2026-06-26T23:54:52.181Z","tf":"1y"},"4543.T":{"why":"","ts":"2026-06-23T02:24:19.096Z","tf":"1y"},"SGRO.L":{"why":"","ts":"2026-06-26T23:54:53.012Z","tf":"1w"},"III.L":{"why":"","ts":"2026-06-28T13:28:20.705Z","tf":"1w"},"BNZL.L":{"why":"","ts":"2026-06-26T23:54:53.027Z","tf":"1w"},"SHEL.L":{"why":"","ts":"2026-06-28T13:28:21.070Z","tf":"1w"},"AAL.L":{"why":"","ts":"2026-06-28T13:28:21.103Z","tf":"1w"},"LSEG.L":{"why":"","ts":"2026-06-28T13:28:21.924Z","tf":"1w"},"GLEN.L":{"why":"","ts":"2026-06-26T23:54:53.508Z","tf":"1w"},"PRU.L":{"why":"","ts":"2026-06-26T23:54:53.513Z","tf":"ytd"},"REL.L":{"why":"","ts":"2026-06-24T23:57:01.964Z","tf":"ytd"},"EXPN.L":{"why":"","ts":"2026-06-28T13:28:21.156Z","tf":"ytd"},"DGE.L":{"why":"","ts":"2026-06-28T13:28:21.228Z","tf":"1y"},"BAYN.DE":{"why":"","ts":"2026-06-28T13:28:24.307Z","tf":"1w"},"MRK.DE":{"why":"Agreed to acquire Bio-Techne for $11.3 billion","ts":"2026-06-28T13:28:24.228Z","tf":"1w"},"MTX.DE":{"why":"","ts":"2026-06-26T23:54:56.112Z","tf":"1w"},"QIA.DE":{"why":"","ts":"2026-06-26T23:54:55.865Z","tf":"1w"},"SRT3.DE":{"why":"","ts":"2026-06-28T13:28:23.951Z","tf":"1w"},"DBK.DE":{"why":"","ts":"2026-06-28T13:28:24.820Z","tf":"1w"},"VOW3.DE":{"why":"Plans to cut 15% of workforce and close four German plants","ts":"2026-06-26T23:54:57.380Z","tf":"1w"},"P911.DE":{"why":"","ts":"2026-06-28T13:28:24.557Z","tf":"1w"},"RHM.DE":{"why":"Germany shelved major warship contract","ts":"2026-06-26T23:54:57.281Z","tf":"1w"},"SY1.DE":{"why":"","ts":"2026-06-28T13:28:24.927Z","tf":"ytd"},"RWE.DE":{"why":"","ts":"2026-06-26T23:54:57.418Z","tf":"ytd"},"DHL.DE":{"why":"","ts":"2026-06-28T13:28:25.670Z","tf":"1y"},"SHL.DE":{"why":"","ts":"2026-06-23T02:24:28.487Z","tf":"1y"},"AEM.TO":{"why":"","ts":"2026-06-26T23:55:00.532Z","tf":"1w"},"GWO.TO":{"why":"","ts":"2026-06-23T23:11:48.498Z","tf":"ytd"},"IMO.TO":{"why":"","ts":"2026-06-23T23:11:47.631Z","tf":"ytd"},"CSU.TO":{"why":"","ts":"2026-06-26T23:55:01.836Z","tf":"1y"},"LONN.SW":{"why":"","ts":"2026-06-28T13:28:30.284Z","tf":"1w"},"KNIN.SW":{"why":"","ts":"2026-06-28T13:28:30.113Z","tf":"1w"},"ROP.SW":{"why":"","ts":"2026-06-28T13:28:30.495Z","tf":"1w"},"STMN.SW":{"why":"","ts":"2026-06-28T13:28:30.976Z","tf":"ytd"},"GALE.SW":{"why":"","ts":"2026-06-26T00:06:34.265Z","tf":"ytd"},"2269.HK":{"why":"","ts":"2026-06-26T23:55:05.151Z","tf":"1w"},"0823.HK":{"why":"","ts":"2026-06-26T23:55:06.131Z","tf":"1w"},"0001.HK":{"why":"Vodafone buys out UK mobile partner","ts":"2026-06-23T02:24:42.631Z","tf":"ytd"},"0005.HK":{"why":"","ts":"2026-06-26T00:06:37.191Z","tf":"ytd"},"1113.HK":{"why":"","ts":"2026-06-26T00:06:37.096Z","tf":"ytd"},"1109.HK":{"why":"","ts":"2026-06-26T23:55:06.915Z","tf":"ytd"},"2688.HK":{"why":"Ditched $12 billion restructuring plan","ts":"2026-06-26T00:06:37.577Z","tf":"ytd"},"ALSEA.MX":{"why":"","ts":"2026-06-26T23:55:08.350Z","tf":"1w"},"AMXB.MX":{"why":"","ts":"2026-06-23T23:11:56.172Z","tf":"ytd"},"WALMEX.MX":{"why":"","ts":"2026-06-26T23:55:08.765Z","tf":"1y"},"GLW":{"why":"","ts":"2026-06-30T02:19:23.444Z","tf":"1d"},"WDC":{"why":"","ts":"2026-06-30T02:19:23.566Z","tf":"1d"},"AMAT":{"why":"","ts":"2026-06-30T02:19:23.581Z","tf":"1d"},"KLAC":{"why":"","ts":"2026-06-30T02:19:24.045Z","tf":"1d"},"AXON":{"why":"Trump bought up to $5M in stock before ICE deal","ts":"2026-06-30T02:19:24.194Z","tf":"1d"},"CHTR":{"why":"S&P 500 futures climb, Charter Communications leads","ts":"2026-06-30T02:19:24.880Z","tf":"1d"},"MLM":{"why":"Agreed to acquire Lhoist North America for $13.5 billion","ts":"2026-06-30T02:19:24.881Z","tf":"1d"},"ULTA":{"why":"","ts":"2026-06-30T02:19:24.969Z","tf":"1d"},"VZ":{"why":"Starlink Mobile threat","ts":"2026-06-30T02:19:25.026Z","tf":"1d"},"HON":{"why":"Aerospace spin-off completed, began trading on Nasdaq","ts":"2026-06-30T02:19:25.764Z","tf":"1d"},"SMCI":{"why":"","ts":"2026-06-30T02:19:25.876Z","tf":"1d"},"CPRT":{"why":"","ts":"2026-06-30T02:19:26.106Z","tf":"1d"},"CRL":{"why":"","ts":"2026-06-30T02:19:26.349Z","tf":"1w"},"MRNA":{"why":"","ts":"2026-06-30T02:19:26.400Z","tf":"1w"},"QCOM":{"why":"","ts":"2026-06-30T02:19:26.732Z","tf":"1w"},"APO":{"why":"","ts":"2026-06-30T02:19:27.023Z","tf":"1w"},"BLDR":{"why":"","ts":"2026-06-30T02:19:27.086Z","tf":"1w"},"ALB":{"why":"","ts":"2026-06-30T02:19:27.627Z","tf":"1w"},"ON":{"why":"","ts":"2026-06-30T02:19:27.774Z","tf":"1w"},"ALAB":{"why":"","ts":"2026-06-30T02:19:27.996Z","tf":"1d"},"SNDK":{"why":"","ts":"2026-06-30T02:19:28.169Z","tf":"ytd"},"STX":{"why":"","ts":"2026-06-30T02:19:28.318Z","tf":"ytd"},"MSTR":{"why":"","ts":"2026-06-30T02:19:28.847Z","tf":"1d"},"SHOP":{"why":"","ts":"2026-06-30T02:19:28.966Z","tf":"1d"},"IDXX":{"why":"","ts":"2026-06-30T02:19:29.003Z","tf":"1d"},"RKLB":{"why":"Acquiring Iridium in historic deal","ts":"2026-06-30T02:19:29.063Z","tf":"1d"},"ROST":{"why":"","ts":"2026-06-30T02:19:29.410Z","tf":"1d"},"PANW":{"why":"","ts":"2026-06-30T02:19:29.825Z","tf":"1w"},"TMUS":{"why":"","ts":"2026-06-30T02:19:29.932Z","tf":"1d"},"DDOG":{"why":"","ts":"2026-06-30T02:19:29.944Z","tf":"1w"},"CRWD":{"why":"","ts":"2026-06-30T02:19:30.483Z","tf":"1w"},"WDAY":{"why":"","ts":"2026-06-30T02:19:30.606Z","tf":"1w"},"KHC":{"why":"KD Ramen lineup expansion","ts":"2026-06-30T02:19:30.879Z","tf":"1w"},"CRWV":{"why":"","ts":"2026-06-30T02:19:31.320Z","tf":"1w"},"TXN":{"why":"","ts":"2026-06-30T02:19:31.467Z","tf":"1w"},"ARM":{"why":"","ts":"2026-06-30T02:19:31.568Z","tf":"1w"},"MPWR":{"why":"","ts":"2026-06-30T02:19:31.914Z","tf":"1w"},"PLTR":{"why":"","ts":"2026-06-30T02:19:32.157Z","tf":"ytd"},"TRI":{"why":"","ts":"2026-06-30T02:19:32.547Z","tf":"ytd"},"IRDM":{"why":"Agreed to be acquired by Rocket Lab","ts":"2026-06-30T02:19:32.796Z","tf":"1d"},"ASTS":{"why":"","ts":"2026-06-30T02:19:32.871Z","tf":"1d"},"NFLX":{"why":"Earnings topped estimates, stock drops after Hastings announcement","ts":"2026-06-30T02:19:33.095Z","tf":"1y"},"DDS":{"why":"","ts":"2026-06-30T02:19:33.328Z","tf":"1d"},"OC":{"why":"Report of unsolicited takeover bids","ts":"2026-06-30T02:19:33.389Z","tf":"1d"},"GAP":{"why":"","ts":"2026-06-30T02:19:33.793Z","tf":"1d"},"CE":{"why":"","ts":"2026-06-30T02:19:33.929Z","tf":"1d"},"LCID":{"why":"","ts":"2026-06-30T02:19:34.214Z","tf":"1w"},"BLD":{"why":"Acquisition by QXO approved by stockholders","ts":"2026-06-30T02:19:34.321Z","tf":"1d"},"CLF":{"why":"","ts":"2026-06-30T02:19:34.670Z","tf":"1w"},"WEN":{"why":"New meme stock status, trading halted","ts":"2026-06-30T02:19:34.761Z","tf":"1w"},"CAR":{"why":"","ts":"2026-06-30T02:19:35.065Z","tf":"1w"},"VSAT":{"why":"","ts":"2026-06-30T02:19:35.351Z","tf":"1d"},"BRBR":{"why":"Q2 earnings miss, cut FY guidance","ts":"2026-06-30T02:19:35.360Z","tf":"1y"},"QDEL":{"why":"Reported exploring sale of testing unit","ts":"2026-06-30T02:19:35.455Z","tf":"1d"},"ALGM":{"why":"","ts":"2026-06-30T02:19:35.484Z","tf":"1d"},"WS":{"why":"","ts":"2026-06-30T02:19:35.769Z","tf":"1d"},"ADNT":{"why":"","ts":"2026-06-30T02:19:35.953Z","tf":"1d"},"SNEX":{"why":"","ts":"2026-06-30T02:19:36.359Z","tf":"1d"},"HWKN":{"why":"","ts":"2026-06-30T02:19:36.492Z","tf":"1d"},"HTZ":{"why":"Funding plan, profit guide","ts":"2026-06-30T02:19:36.588Z","tf":"1d"},"MLKN":{"why":"","ts":"2026-06-30T02:19:36.633Z","tf":"1w"},"NEO":{"why":"","ts":"2026-06-30T02:19:36.909Z","tf":"1w"},"CABO":{"why":"","ts":"2026-06-30T02:19:37.130Z","tf":"1w"},"EFOR":{"why":"","ts":"2026-06-30T02:19:37.474Z","tf":"ytd"},"OUST":{"why":"","ts":"2026-06-30T02:19:37.631Z","tf":"1d"},"EMBC":{"why":"","ts":"2026-06-30T02:19:37.718Z","tf":"ytd"},"VC":{"why":"","ts":"2026-06-30T02:19:37.767Z","tf":"1w"},"SLS":{"why":"","ts":"2026-06-30T02:19:37.966Z","tf":"1d"},"LRMR":{"why":"","ts":"2026-06-30T02:19:38.239Z","tf":"1d"},"TEAD":{"why":"","ts":"2026-06-30T02:19:38.339Z","tf":"1d"},"WEST":{"why":"","ts":"2026-06-30T02:19:38.344Z","tf":"1d"},"CLPT":{"why":"","ts":"2026-06-30T02:19:38.802Z","tf":"1w"},"FCEL":{"why":"","ts":"2026-06-30T02:19:38.802Z","tf":"1d"},"RGNX":{"why":"FDA alignment on NAVSUNLI BLA resubmission for accelerated approval","ts":"2026-06-30T02:19:39.147Z","tf":"1w"},"ARAY":{"why":"","ts":"2026-06-30T02:19:39.386Z","tf":"1w"},"AMC":{"why":"","ts":"2026-06-30T02:19:39.629Z","tf":"1w"},"DOMO":{"why":"","ts":"2026-06-30T02:19:39.682Z","tf":"1w"},"ALOY":{"why":"Private Placement of Securities","ts":"2026-06-30T02:19:40.030Z","tf":"1w"},"ADCT":{"why":"Strategic reorganization to support ZYNLONTA growth opportunities","ts":"2026-06-30T02:19:40.273Z","tf":"ytd"},"BN.PA":{"why":"","ts":"2026-06-30T02:19:40.454Z","tf":"1d"},"WLN.PA":{"why":"","ts":"2026-06-30T02:19:40.664Z","tf":"1d"},"BE":{"why":"Partnering to power AI infrastructure build-out","ts":"2026-06-30T02:19:40.714Z","tf":"1y"},"LENZ":{"why":"","ts":"2026-06-30T02:19:40.715Z","tf":"1y"},"EDEN.PA":{"why":"","ts":"2026-06-30T02:19:40.911Z","tf":"1d"},"DSY.PA":{"why":"","ts":"2026-06-30T02:19:41.190Z","tf":"1d"},"MT.AS":{"why":"","ts":"2026-06-30T02:19:41.428Z","tf":"1d"},"EL.PA":{"why":"","ts":"2026-06-30T02:19:41.592Z","tf":"1d"},"ALO.PA":{"why":"","ts":"2026-06-30T02:19:41.748Z","tf":"1d"},"STLAP.PA":{"why":"","ts":"2026-06-30T02:19:41.980Z","tf":"1d"},"SAN.PA":{"why":"","ts":"2026-06-30T02:19:41.992Z","tf":"1d"},"AC.PA":{"why":"","ts":"2026-06-30T02:19:42.291Z","tf":"1d"},"STMPA.PA":{"why":"","ts":"2026-06-30T02:19:42.575Z","tf":"1d"},"ASM.AS":{"why":"","ts":"2026-06-30T02:19:42.640Z","tf":"1d"},"SAF.PA":{"why":"","ts":"2026-06-30T02:19:42.880Z","tf":"1d"},"ASML.AS":{"why":"","ts":"2026-06-30T02:19:43.171Z","tf":"1d"},"DSFIR.AS":{"why":"","ts":"2026-06-30T02:19:43.175Z","tf":"1d"},"ABN.AS":{"why":"","ts":"2026-06-30T02:19:43.343Z","tf":"1d"},"PRX.AS":{"why":"Profit jumps, targets $5 billion buyback, more acquisitions","ts":"2026-06-30T02:19:43.522Z","tf":"1d"},"KPN.AS":{"why":"","ts":"2026-06-30T02:19:43.651Z","tf":"1d"},"ASRNL.AS":{"why":"","ts":"2026-06-30T02:19:43.811Z","tf":"1d"},"UMG.AS":{"why":"","ts":"2026-06-30T02:19:43.821Z","tf":"1d"},"IMCD.AS":{"why":"","ts":"2026-06-30T02:19:44.097Z","tf":"1d"},"BESI.AS":{"why":"","ts":"2026-06-30T02:19:44.301Z","tf":"1d"},"AKZA.AS":{"why":"","ts":"2026-06-30T02:19:44.312Z","tf":"1d"},"MICC.AS":{"why":"","ts":"2026-06-30T02:19:44.644Z","tf":"1w"},"AD.AS":{"why":"","ts":"2026-06-30T02:19:44.674Z","tf":"1w"},"SBMO.AS":{"why":"","ts":"2026-06-30T02:19:45.003Z","tf":"1w"},"HEIA.AS":{"why":"Named outsider Rafael Oliveira as CEO","ts":"2026-06-30T02:19:45.044Z","tf":"1w"},"009150.KS":{"why":"","ts":"2026-06-30T02:19:45.121Z","tf":"1d"},"WKL.AS":{"why":"","ts":"2026-06-30T02:19:45.354Z","tf":"ytd"},"EXO.AS":{"why":"Swing to net loss, weak results at listed companies","ts":"2026-06-30T02:19:45.434Z","tf":"ytd"},"105560.KS":{"why":"","ts":"2026-06-30T02:19:45.613Z","tf":"1d"},"005930.KS":{"why":"","ts":"2026-06-30T02:19:46.046Z","tf":"1d"},"138040.KS":{"why":"","ts":"2026-06-30T02:19:46.080Z","tf":"1d"},"010950.KS":{"why":"","ts":"2026-06-30T02:19:46.461Z","tf":"1d"},"066570.KS":{"why":"Unveiled new StanbyME 2 Max personal screen with larger 4K display","ts":"2026-06-30T02:19:46.511Z","tf":"1d"},"011170.KS":{"why":"","ts":"2026-06-30T02:19:46.756Z","tf":"1d"},"090430.KS":{"why":"","ts":"2026-06-30T02:19:47.049Z","tf":"1d"},"051910.KS":{"why":"","ts":"2026-06-30T02:19:47.136Z","tf":"1d"},"003670.KS":{"why":"","ts":"2026-06-30T02:19:47.162Z","tf":"1d"},"207940.KS":{"why":"","ts":"2026-06-30T02:19:47.393Z","tf":"1d"},"373220.KS":{"why":"","ts":"2026-06-30T02:19:47.617Z","tf":"1d"},"068270.KS":{"why":"","ts":"2026-06-30T02:19:47.645Z","tf":"1w"},"055550.KS":{"why":"","ts":"2026-06-30T02:19:47.846Z","tf":"1w"},"316140.KS":{"why":"","ts":"2026-06-30T02:19:47.905Z","tf":"1w"},"047810.KS":{"why":"South Korean defense stocks surge on post-Iran-war sales prospects","ts":"2026-06-30T02:19:48.431Z","tf":"1w"},"032830.KS":{"why":"","ts":"2026-06-30T02:19:48.972Z","tf":"1w"},"006400.KS":{"why":"","ts":"2026-06-30T02:19:48.972Z","tf":"1y"},"015760.KS":{"why":"","ts":"2026-06-30T02:19:48.972Z","tf":"ytd"},"000660.KS":{"why":"Nasdaq debut; multiyear deal with Nvidia; HBM4E chip samples","ts":"2026-06-30T02:19:48.972Z","tf":"ytd"},"6861.T":{"why":"","ts":"2026-06-30T02:19:49.542Z","tf":"1d"},"6981.T":{"why":"Robust AI demand tightens MLCC supply, enabling medium-term growth","ts":"2026-06-30T02:19:49.560Z","tf":"1d"},"6954.T":{"why":"","ts":"2026-06-30T02:19:49.655Z","tf":"1d"},"6752.T":{"why":"","ts":"2026-06-30T02:19:49.776Z","tf":"1d"},"8035.T":{"why":"","ts":"2026-06-30T02:19:49.819Z","tf":"1d"},"6273.T":{"why":"","ts":"2026-06-30T02:19:50.230Z","tf":"1d"},"6501.T":{"why":"","ts":"2026-06-30T02:19:50.354Z","tf":"1d"},"4568.T":{"why":"","ts":"2026-06-30T02:19:50.883Z","tf":"1d"},"7974.T":{"why":"","ts":"2026-06-30T02:19:50.884Z","tf":"1d"},"7269.T":{"why":"","ts":"2026-06-30T02:19:51.190Z","tf":"1d"},"9983.T":{"why":"","ts":"2026-06-30T02:19:51.226Z","tf":"1d"},"7203.T":{"why":"May sales fall for fourth consecutive month","ts":"2026-06-30T02:19:51.720Z","tf":"1d"},"4063.T":{"why":"","ts":"2026-06-30T02:19:51.802Z","tf":"1w"},"6503.T":{"why":"","ts":"2026-06-30T02:19:52.163Z","tf":"1w"},"7267.T":{"why":"Agreement with Honda on solid-state battery technology","ts":"2026-06-30T02:19:52.264Z","tf":"1w"},"6594.T":{"why":"","ts":"2026-06-30T02:19:52.310Z","tf":"1w"},"8058.T":{"why":"","ts":"2026-06-30T02:19:52.460Z","tf":"1w"},"6645.T":{"why":"","ts":"2026-06-30T02:19:52.843Z","tf":"1d"},"9984.T":{"why":"Vision Fund CFO leaving company","ts":"2026-06-30T02:19:53.149Z","tf":"1w"},"8267.T":{"why":"","ts":"2026-06-30T02:19:53.236Z","tf":"1d"},"9020.T":{"why":"","ts":"2026-06-30T02:19:53.545Z","tf":"ytd"},"4689.T":{"why":"","ts":"2026-06-30T02:19:53.645Z","tf":"1d"},"6701.T":{"why":"","ts":"2026-06-30T02:19:53.648Z","tf":"1d"},"7733.T":{"why":"","ts":"2026-06-30T02:19:53.918Z","tf":"1d"},"9843.T":{"why":"","ts":"2026-06-30T02:19:54.079Z","tf":"1d"},"7832.T":{"why":"","ts":"2026-06-30T02:19:54.281Z","tf":"1d"},"4911.T":{"why":"","ts":"2026-06-30T02:19:54.356Z","tf":"1w"},"4307.T":{"why":"","ts":"2026-06-30T02:19:54.377Z","tf":"1w"},"8725.T":{"why":"","ts":"2026-06-30T02:19:54.552Z","tf":"1w"},"5802.T":{"why":"","ts":"2026-06-30T02:19:55.112Z","tf":"1w"},"5713.T":{"why":"","ts":"2026-06-30T02:19:55.356Z","tf":"1w"},"6762.T":{"why":"Analyst note: MLCC expectations too high","ts":"2026-06-30T02:19:55.459Z","tf":"1w"},"6963.T":{"why":"Denso CEO hopes for 'significant synergies' from proposed acquisition","ts":"2026-06-30T02:19:55.554Z","tf":"ytd"},"2802.T":{"why":"Palliser Capital publishes value enhancement plan","ts":"2026-06-30T02:19:55.653Z","tf":"ytd"},"FLTR.L":{"why":"","ts":"2026-06-30T02:19:56.174Z","tf":"1d"},"7270.T":{"why":"","ts":"2026-06-30T02:19:56.340Z","tf":"ytd"},"6857.T":{"why":"","ts":"2026-06-30T02:19:56.535Z","tf":"1y"},"RKT.L":{"why":"","ts":"2026-06-30T02:19:56.757Z","tf":"1d"},"9697.T":{"why":"","ts":"2026-06-30T02:19:56.784Z","tf":"1y"},"9501.T":{"why":"Annual loss of 454.3 billion yen","ts":"2026-06-30T02:19:56.784Z","tf":"ytd"},"AZN.L":{"why":"","ts":"2026-06-30T02:19:56.799Z","tf":"1d"},"CPG.L":{"why":"","ts":"2026-06-30T02:19:57.075Z","tf":"1d"},"STAN.L":{"why":"","ts":"2026-06-30T02:19:57.298Z","tf":"1d"},"HSBA.L":{"why":"","ts":"2026-06-30T02:19:57.325Z","tf":"1d"},"TSCO.L":{"why":"","ts":"2026-06-30T02:19:57.342Z","tf":"1d"},"RR.L":{"why":"","ts":"2026-06-30T02:19:57.573Z","tf":"1d"},"WTB.L":{"why":"","ts":"2026-06-30T02:19:57.816Z","tf":"1d"},"BP.L":{"why":"","ts":"2026-06-30T02:19:57.871Z","tf":"1d"},"BARC.L":{"why":"","ts":"2026-06-30T02:19:57.980Z","tf":"1d"},"RIO.L":{"why":"","ts":"2026-06-30T02:19:58.067Z","tf":"1w"},"BATS.L":{"why":"Cuts 9,000 jobs as turnaround program intensifies","ts":"2026-06-30T02:19:58.209Z","tf":"1d"},"VNA.DE":{"why":"","ts":"2026-06-30T02:19:58.423Z","tf":"1d"},"BEI.DE":{"why":"","ts":"2026-06-30T02:19:58.608Z","tf":"1d"},"SAP.DE":{"why":"","ts":"2026-06-30T02:19:58.673Z","tf":"1d"},"HEN3.DE":{"why":"","ts":"2026-06-30T02:19:58.889Z","tf":"1d"},"ADS.DE":{"why":"","ts":"2026-06-30T02:19:58.953Z","tf":"1d"},"CBK.DE":{"why":"","ts":"2026-06-30T02:19:59.180Z","tf":"1d"},"BMW.DE":{"why":"","ts":"2026-06-30T02:19:59.246Z","tf":"1d"},"MBG.DE":{"why":"","ts":"2026-06-30T02:19:59.673Z","tf":"1d"},"IFX.DE":{"why":"","ts":"2026-06-30T02:19:59.683Z","tf":"1d"},"ENR.DE":{"why":"","ts":"2026-06-30T02:20:00.112Z","tf":"1d"},"ZAL.DE":{"why":"German regulator probes €1.1bn deal disclosure","ts":"2026-06-30T02:20:00.191Z","tf":"1d"},"MFC.TO":{"why":"","ts":"2026-06-30T02:20:00.430Z","tf":"1d"},"PAH3.DE":{"why":"Key shareholder pitches producing China car models in Germany","ts":"2026-06-30T02:20:00.625Z","tf":"1d"},"CVE.TO":{"why":"","ts":"2026-06-30T02:20:00.921Z","tf":"1d"},"MG.TO":{"why":"","ts":"2026-06-30T02:20:01.367Z","tf":"1d"},"RY.TO":{"why":"","ts":"2026-06-30T02:20:01.560Z","tf":"1d"},"BMO.TO":{"why":"","ts":"2026-06-30T02:20:01.849Z","tf":"1d"},"TD.TO":{"why":"","ts":"2026-06-30T02:20:02.045Z","tf":"1d"},"MRU.TO":{"why":"Ongoing strike to take a bite out of Q3 earnings","ts":"2026-06-30T02:20:02.339Z","tf":"1d"},"T.TO":{"why":"","ts":"2026-06-30T02:20:02.370Z","tf":"1d"},"RCI-B.TO":{"why":"","ts":"2026-06-30T02:20:02.389Z","tf":"1d"},"ATZ.TO":{"why":"","ts":"2026-06-30T02:20:02.731Z","tf":"1d"},"BCE.TO":{"why":"","ts":"2026-06-30T02:20:03.026Z","tf":"1d"},"FNV.TO":{"why":"","ts":"2026-06-30T02:20:03.614Z","tf":"1d"},"ATD.TO":{"why":"Beat estimates on strong fuel margins","ts":"2026-06-30T02:20:03.614Z","tf":"1w"},"OTEX.TO":{"why":"","ts":"2026-06-30T02:20:03.761Z","tf":"1w"},"GRGD.TO":{"why":"","ts":"2026-06-30T02:20:03.958Z","tf":"1w"},"WCN.TO":{"why":"","ts":"2026-06-30T02:20:04.299Z","tf":"1w"},"TRI.TO":{"why":"","ts":"2026-06-30T02:20:04.847Z","tf":"1w"},"TECK-B.TO":{"why":"","ts":"2026-06-30T02:20:04.994Z","tf":"1w"},"SHOP.TO":{"why":"","ts":"2026-06-30T02:20:04.996Z","tf":"1w"},"ABX.TO":{"why":"","ts":"2026-06-30T02:20:05.141Z","tf":"1w"},"WPM.TO":{"why":"","ts":"2026-06-30T02:20:05.537Z","tf":"1w"},"TEMN.SW":{"why":"","ts":"2026-06-30T02:20:05.703Z","tf":"1d"},"VACN.SW":{"why":"","ts":"2026-06-30T02:20:05.925Z","tf":"1d"},"GIB-A.TO":{"why":"AI fears crush share price, new CEO named","ts":"2026-06-30T02:20:06.079Z","tf":"ytd"},"CFR.SW":{"why":"","ts":"2026-06-30T02:20:06.149Z","tf":"1d"},"WSP.TO":{"why":"","ts":"2026-06-30T02:20:06.176Z","tf":"ytd"},"ADEN.SW":{"why":"","ts":"2026-06-30T02:20:06.280Z","tf":"1d"},"BAER.SW":{"why":"","ts":"2026-06-30T02:20:06.586Z","tf":"1d"},"ALC.SW":{"why":"","ts":"2026-06-30T02:20:06.799Z","tf":"1d"},"BARN.SW":{"why":"","ts":"2026-06-30T02:20:06.871Z","tf":"1d"},"SOON.SW":{"why":"","ts":"2026-06-30T02:20:06.883Z","tf":"1d"},"NESN.SW":{"why":"","ts":"2026-06-30T02:20:06.928Z","tf":"1d"},"CLN.SW":{"why":"","ts":"2026-06-30T02:20:07.138Z","tf":"1d"},"GIVN.SW":{"why":"","ts":"2026-06-30T02:20:07.482Z","tf":"1w"},"SIKA.SW":{"why":"","ts":"2026-06-30T02:20:07.546Z","tf":"1d"},"HOLN.SW":{"why":"","ts":"2026-06-30T02:20:07.562Z","tf":"1d"},"LISN.SW":{"why":"","ts":"2026-06-30T02:20:07.727Z","tf":"1w"},"UBSG.SW":{"why":"","ts":"2026-06-30T02:20:08.063Z","tf":"1w"},"ABBN.SW":{"why":"","ts":"2026-06-30T02:20:08.507Z","tf":"1w"},"NOVN.SW":{"why":"Strategic collaboration with Orionis Biosciences for molecular glue medicines","ts":"2026-06-30T02:20:08.977Z","tf":"ytd"},"UHR.SW":{"why":"Royal Pop launch triggers consumer frenzy, resale prices soar","ts":"2026-06-30T02:20:09.027Z","tf":"ytd"},"9888.HK":{"why":"","ts":"2026-06-30T02:20:09.061Z","tf":"1d"},"LOGN.SW":{"why":"","ts":"2026-06-30T02:20:09.074Z","tf":"1w"},"PGHN.SW":{"why":"","ts":"2026-06-30T02:20:09.522Z","tf":"ytd"},"9999.HK":{"why":"","ts":"2026-06-30T02:20:09.714Z","tf":"1d"},"3690.HK":{"why":"","ts":"2026-06-30T02:20:09.796Z","tf":"1d"},"0700.HK":{"why":"","ts":"2026-06-30T02:20:09.922Z","tf":"1d"},"6086.HK":{"why":"","ts":"2026-06-30T02:20:10.013Z","tf":"1d"},"2382.HK":{"why":"Expands on \"Optics + Artificial Intelligence\" Strategy","ts":"2026-06-30T02:20:10.305Z","tf":"1d"},"0175.HK":{"why":"","ts":"2026-06-30T02:20:10.464Z","tf":"1d"},"0883.HK":{"why":"","ts":"2026-06-30T02:20:10.544Z","tf":"1d"},"2628.HK":{"why":"","ts":"2026-06-30T02:20:10.592Z","tf":"1d"},"2331.HK":{"why":"","ts":"2026-06-30T02:20:10.875Z","tf":"1d"},"0857.HK":{"why":"","ts":"2026-06-30T02:20:10.951Z","tf":"1d"},"1093.HK":{"why":"","ts":"2026-06-30T02:20:11.161Z","tf":"1w"},"0016.HK":{"why":"","ts":"2026-06-30T02:20:11.467Z","tf":"ytd"},"2020.HK":{"why":"","ts":"2026-06-30T02:20:11.625Z","tf":"1w"},"0267.HK":{"why":"","ts":"2026-06-30T02:20:11.723Z","tf":"1d"},"0762.HK":{"why":"","ts":"2026-06-30T02:20:11.920Z","tf":"1w"},"2313.HK":{"why":"","ts":"2026-06-30T02:20:12.558Z","tf":"ytd"},"3988.HK":{"why":"possible change in shareholding rule","ts":"2026-06-30T02:20:12.609Z","tf":"ytd"},"1024.HK":{"why":"","ts":"2026-06-30T02:20:12.856Z","tf":"ytd"},"9988.HK":{"why":"","ts":"2026-06-30T02:20:13.005Z","tf":"ytd"},"1810.HK":{"why":"","ts":"2026-06-30T02:20:13.250Z","tf":"ytd"},"0960.HK":{"why":"","ts":"2026-06-30T02:20:13.293Z","tf":"1y"},"ALPEKA.MX":{"why":"","ts":"2026-06-30T02:20:13.388Z","tf":"1d"},"GENTERA.MX":{"why":"","ts":"2026-06-30T02:20:13.535Z","tf":"1d"},"ORBIA.MX":{"why":"","ts":"2026-06-30T02:20:13.880Z","tf":"1d"},"1211.HK":{"why":"US labels company as aiding Chinese military","ts":"2026-06-30T02:20:13.936Z","tf":"1y"},"CUERVO.MX":{"why":"","ts":"2026-06-30T02:20:14.017Z","tf":"1d"},"BBAJIOO.MX":{"why":"","ts":"2026-06-30T02:20:14.049Z","tf":"1d"},"RA.MX":{"why":"","ts":"2026-06-30T02:20:14.364Z","tf":"1d"},"LABB.MX":{"why":"","ts":"2026-06-30T02:20:14.479Z","tf":"1d"},"KIMBERA.MX":{"why":"","ts":"2026-06-30T02:20:14.512Z","tf":"1d"},"AC.MX":{"why":"","ts":"2026-06-30T02:20:14.532Z","tf":"1d"},"CHDRAUIB.MX":{"why":"","ts":"2026-06-30T02:20:14.586Z","tf":"1d"},"CEMEXCPO.MX":{"why":"","ts":"2026-06-30T02:20:14.937Z","tf":"1d"},"BOLSAA.MX":{"why":"","ts":"2026-06-30T02:20:15.026Z","tf":"1d"},"MEGACPO.MX":{"why":"","ts":"2026-06-30T02:20:15.094Z","tf":"1w"},"FUNO11.MX":{"why":"","ts":"2026-06-30T02:20:15.099Z","tf":"1w"},"FEMSAUBD.MX":{"why":"","ts":"2026-06-30T02:20:15.147Z","tf":"1w"},"GCARSOA1.MX":{"why":"","ts":"2026-06-30T02:20:15.591Z","tf":"1w"},"PE&OLES.MX":{"why":"","ts":"2026-06-30T02:20:15.629Z","tf":"ytd"},"PINFRA.MX":{"why":"","ts":"2026-06-30T02:20:15.696Z","tf":"1y"},"GMEXICOB.MX":{"why":"","ts":"2026-06-30T02:20:15.918Z","tf":"1w"},"GFNORTEO.MX":{"why":"raised $1.35 billion in hybrid debt sale","ts":"2026-06-30T02:20:15.963Z","tf":"1w"},"MFEB.MI":{"why":"","ts":"2026-06-30T02:20:16.166Z","tf":"1d"},"BNJ.AS":{"why":"","ts":"2026-06-30T02:20:16.220Z","tf":"1d"},"TIT.MI":{"why":"","ts":"2026-06-30T02:20:16.408Z","tf":"1d"},"MFEA.MI":{"why":"","ts":"2026-06-30T02:20:16.504Z","tf":"1d"},"MMB.PA":{"why":"","ts":"2026-06-30T02:20:16.512Z","tf":"1d"},"VPLAY-B.ST":{"why":"","ts":"2026-06-30T02:20:16.703Z","tf":"1d"},"TEF.MC":{"why":"","ts":"2026-06-30T02:20:16.917Z","tf":"1d"},"PRS.MC":{"why":"","ts":"2026-06-30T02:20:16.923Z","tf":"1d"},"SGE.L":{"why":"","ts":"2026-06-30T02:20:17.054Z","tf":"1d"},"STMMI.MI":{"why":"","ts":"2026-06-30T02:20:17.094Z","tf":"1d"},"IDR.MC":{"why":"","ts":"2026-06-30T02:20:17.108Z","tf":"1d"},"CAN.L":{"why":"","ts":"2026-06-30T02:20:17.387Z","tf":"1d"},"RMV.L":{"why":"","ts":"2026-06-30T02:20:17.551Z","tf":"1w"},"NOKIA.HE":{"why":"","ts":"2026-06-30T02:20:17.571Z","tf":"1d"},"WAF.DE":{"why":"","ts":"2026-06-30T02:20:17.589Z","tf":"1d"},"AUTO.L":{"why":"","ts":"2026-06-30T02:20:17.630Z","tf":"1w"},"ATE.PA":{"why":"","ts":"2026-06-30T02:20:18.008Z","tf":"1w"},"AMS.MC":{"why":"","ts":"2026-06-30T02:20:18.767Z","tf":"ytd"},"DHER.DE":{"why":"Uber takeover interest, stake increases","ts":"2026-06-30T02:20:19.010Z","tf":"ytd"}}